[
    {
        "date": "2009-04-04",
        "rank": "1",
        "song": "Right Round",
        "artist": "Flo Rida",
        "last-week": "1",
        "peak-rank": "1",
        "weeks-on-board": "8"
    },
    {
        "date": "2009-04-04",
        "rank": "2",
        "song": "Poker Face",
        "artist": "Lady Gaga",
        "last-week": "3",
        "peak-rank": "2",
        "weeks-on-board": "14"
    },
    {
        "date": "2009-04-04",
        "rank": "3",
        "song": "Kiss Me Thru The Phone",
        "artist": "Soulja Boy Tell 'em Featuring Sammie",
        "last-week": "4",
        "peak-rank": "3",
        "weeks-on-board": "13"
    },
    {
        "date": "2009-04-04",
        "rank": "4",
        "song": "Dead And Gone",
        "artist": "T.I. Featuring Justin Timberlake",
        "last-week": "2",
        "peak-rank": "2",
        "weeks-on-board": "16"
    },
    {
        "date": "2009-04-04",
        "rank": "5",
        "song": "Gives You Hell",
        "artist": "The All-American Rejects",
        "last-week": "6",
        "peak-rank": "4",
        "weeks-on-board": "19"
    },
    {
        "date": "2009-04-04",
        "rank": "6",
        "song": "My Life Would Suck Without You",
        "artist": "Kelly Clarkson",
        "last-week": "5",
        "peak-rank": "1",
        "weeks-on-board": "10"
    },
    {
        "date": "2009-04-04",
        "rank": "7",
        "song": "Blame It",
        "artist": "Jamie Foxx Featuring T-Pain",
        "last-week": "8",
        "peak-rank": "7",
        "weeks-on-board": "10"
    },
    {
        "date": "2009-04-04",
        "rank": "8",
        "song": "Heartless",
        "artist": "Kanye West",
        "last-week": "7",
        "peak-rank": "2",
        "weeks-on-board": "20"
    },
    {
        "date": "2009-04-04",
        "rank": "9",
        "song": "I Told You So",
        "artist": "Carrie Underwood Featuring Randy Travis",
        "last-week": "57",
        "peak-rank": "9",
        "weeks-on-board": "6"
    },
    {
        "date": "2009-04-04",
        "rank": "10",
        "song": "Just Dance",
        "artist": "Lady Gaga Featuring Colby O'Donis",
        "last-week": "10",
        "peak-rank": "1",
        "weeks-on-board": "33"
    },
    {
        "date": "2009-04-04",
        "rank": "11",
        "song": "The Climb",
        "artist": "Miley Cyrus",
        "last-week": "9",
        "peak-rank": "6",
        "weeks-on-board": "3"
    },
    {
        "date": "2009-04-04",
        "rank": "12",
        "song": "Mad",
        "artist": "Ne-Yo",
        "last-week": "12",
        "peak-rank": "11",
        "weeks-on-board": "16"
    },
    {
        "date": "2009-04-04",
        "rank": "13",
        "song": "Love Story",
        "artist": "Taylor Swift",
        "last-week": "13",
        "peak-rank": "4",
        "weeks-on-board": "28"
    },
    {
        "date": "2009-04-04",
        "rank": "14",
        "song": "I Love College",
        "artist": "Asher Roth",
        "last-week": "17",
        "peak-rank": "14",
        "weeks-on-board": "6"
    },
    {
        "date": "2009-04-04",
        "rank": "15",
        "song": "Turnin Me On",
        "artist": "Keri Hilson Featuring Lil Wayne",
        "last-week": "15",
        "peak-rank": "15",
        "weeks-on-board": "14"
    },
    {
        "date": "2009-04-04",
        "rank": "16",
        "song": "You Found Me",
        "artist": "The Fray",
        "last-week": "16",
        "peak-rank": "7",
        "weeks-on-board": "18"
    },
    {
        "date": "2009-04-04",
        "rank": "17",
        "song": "Circus",
        "artist": "Britney Spears",
        "last-week": "14",
        "peak-rank": "3",
        "weeks-on-board": "16"
    },
    {
        "date": "2009-04-04",
        "rank": "18",
        "song": "Day 'N' Nite",
        "artist": "Kid Cudi",
        "last-week": "23",
        "peak-rank": "18",
        "weeks-on-board": "10"
    },
    {
        "date": "2009-04-04",
        "rank": "19",
        "song": "Sober",
        "artist": "P!nk",
        "last-week": "20",
        "peak-rank": "15",
        "weeks-on-board": "17"
    },
    {
        "date": "2009-04-04",
        "rank": "20",
        "song": "Beautiful",
        "artist": "Akon Featuring Colby O'Donis & Kardinal Offishall",
        "last-week": "19",
        "peak-rank": "19",
        "weeks-on-board": "16"
    },
    {
        "date": "2009-04-04",
        "rank": "21",
        "song": "Here Comes Goodbye",
        "artist": "Rascal Flatts",
        "last-week": "11",
        "peak-rank": "11",
        "weeks-on-board": "4"
    },
    {
        "date": "2009-04-04",
        "rank": "22",
        "song": "Crack A Bottle",
        "artist": "Eminem, Dr. Dre & 50 Cent",
        "last-week": "18",
        "peak-rank": "1",
        "weeks-on-board": "10"
    },
    {
        "date": "2009-04-04",
        "rank": "23",
        "song": "Rockin' That Thang",
        "artist": "The-Dream",
        "last-week": "22",
        "peak-rank": "22",
        "weeks-on-board": "13"
    },
    {
        "date": "2009-04-04",
        "rank": "24",
        "song": "I'm Yours",
        "artist": "Jason Mraz",
        "last-week": "25",
        "peak-rank": "6",
        "weeks-on-board": "49"
    },
    {
        "date": "2009-04-04",
        "rank": "25",
        "song": "Sugar",
        "artist": "Flo Rida Featuring Wynter",
        "last-week": "",
        "peak-rank": "25",
        "weeks-on-board": "1"
    },
    {
        "date": "2009-04-04",
        "rank": "26",
        "song": "If U Seek Amy",
        "artist": "Britney Spears",
        "last-week": "35",
        "peak-rank": "26",
        "weeks-on-board": "6"
    },
    {
        "date": "2009-04-04",
        "rank": "27",
        "song": "Love Sex Magic",
        "artist": "Ciara Featuring Justin Timberlake",
        "last-week": "86",
        "peak-rank": "27",
        "weeks-on-board": "2"
    },
    {
        "date": "2009-04-04",
        "rank": "28",
        "song": "Halo",
        "artist": "Beyonce",
        "last-week": "32",
        "peak-rank": "28",
        "weeks-on-board": "9"
    },
    {
        "date": "2009-04-04",
        "rank": "29",
        "song": "Let It Rock",
        "artist": "Kevin Rudolf Featuring Lil Wayne",
        "last-week": "26",
        "peak-rank": "5",
        "weeks-on-board": "30"
    },
    {
        "date": "2009-04-04",
        "rank": "30",
        "song": "Single Ladies (Put A Ring On It)",
        "artist": "Beyonce",
        "last-week": "24",
        "peak-rank": "1",
        "weeks-on-board": "23"
    },
    {
        "date": "2009-04-04",
        "rank": "31",
        "song": "I Hate This Part",
        "artist": "The Pussycat Dolls",
        "last-week": "27",
        "peak-rank": "11",
        "weeks-on-board": "17"
    },
    {
        "date": "2009-04-04",
        "rank": "32",
        "song": "White Horse",
        "artist": "Taylor Swift",
        "last-week": "29",
        "peak-rank": "13",
        "weeks-on-board": "19"
    },
    {
        "date": "2009-04-04",
        "rank": "33",
        "song": "Hot Revolver",
        "artist": "Lil Wayne",
        "last-week": "",
        "peak-rank": "33",
        "weeks-on-board": "1"
    },
    {
        "date": "2009-04-04",
        "rank": "34",
        "song": "Hot N Cold",
        "artist": "Katy Perry",
        "last-week": "28",
        "peak-rank": "3",
        "weeks-on-board": "34"
    },
    {
        "date": "2009-04-04",
        "rank": "35",
        "song": "Then",
        "artist": "Brad Paisley",
        "last-week": "",
        "peak-rank": "35",
        "weeks-on-board": "1"
    },
    {
        "date": "2009-04-04",
        "rank": "36",
        "song": "How Do You Sleep?",
        "artist": "Jesse McCartney Featuring Ludacris",
        "last-week": "34",
        "peak-rank": "33",
        "weeks-on-board": "7"
    },
    {
        "date": "2009-04-04",
        "rank": "37",
        "song": "Viva La Vida",
        "artist": "Coldplay",
        "last-week": "33",
        "peak-rank": "1",
        "weeks-on-board": "46"
    },
    {
        "date": "2009-04-04",
        "rank": "38",
        "song": "Diva",
        "artist": "Beyonce",
        "last-week": "30",
        "peak-rank": "19",
        "weeks-on-board": "14"
    },
    {
        "date": "2009-04-04",
        "rank": "39",
        "song": "Live Your Life",
        "artist": "T.I. Featuring Rihanna",
        "last-week": "31",
        "peak-rank": "1",
        "weeks-on-board": "26"
    },
    {
        "date": "2009-04-04",
        "rank": "40",
        "song": "Second Chance",
        "artist": "Shinedown",
        "last-week": "39",
        "peak-rank": "39",
        "weeks-on-board": "17"
    },
    {
        "date": "2009-04-04",
        "rank": "41",
        "song": "It Won't Be Like This For Long",
        "artist": "Darius Rucker",
        "last-week": "36",
        "peak-rank": "36",
        "weeks-on-board": "12"
    },
    {
        "date": "2009-04-04",
        "rank": "42",
        "song": "Don't Trust Me",
        "artist": "3OH!3",
        "last-week": "45",
        "peak-rank": "42",
        "weeks-on-board": "15"
    },
    {
        "date": "2009-04-04",
        "rank": "43",
        "song": "She's Country",
        "artist": "Jason Aldean",
        "last-week": "42",
        "peak-rank": "42",
        "weeks-on-board": "10"
    },
    {
        "date": "2009-04-04",
        "rank": "44",
        "song": "I Know You Want Me (Calle Ocho)",
        "artist": "Pitbull",
        "last-week": "50",
        "peak-rank": "44",
        "weeks-on-board": "4"
    },
    {
        "date": "2009-04-04",
        "rank": "45",
        "song": "Gotta Be Somebody",
        "artist": "Nickelback",
        "last-week": "37",
        "peak-rank": "10",
        "weeks-on-board": "25"
    },
    {
        "date": "2009-04-04",
        "rank": "46",
        "song": "1, 2, 3, 4",
        "artist": "Plain White T's",
        "last-week": "49",
        "peak-rank": "46",
        "weeks-on-board": "9"
    },
    {
        "date": "2009-04-04",
        "rank": "47",
        "song": "Ain't I",
        "artist": "Yung L.A. Featuring Young Dro & T.I.",
        "last-week": "47",
        "peak-rank": "47",
        "weeks-on-board": "8"
    },
    {
        "date": "2009-04-04",
        "rank": "48",
        "song": "Jai Ho! (You Are My Destiny)",
        "artist": "A R Rahman & The Pussycat Dolls Featuring Nicole Scherzinger",
        "last-week": "48",
        "peak-rank": "15",
        "weeks-on-board": "5"
    },
    {
        "date": "2009-04-04",
        "rank": "49",
        "song": "So What",
        "artist": "P!nk",
        "last-week": "46",
        "peak-rank": "1",
        "weeks-on-board": "31"
    },
    {
        "date": "2009-04-04",
        "rank": "50",
        "song": "Sweet Thing",
        "artist": "Keith Urban",
        "last-week": "38",
        "peak-rank": "30",
        "weeks-on-board": "19"
    },
    {
        "date": "2009-04-04",
        "rank": "51",
        "song": "Thinking Of You",
        "artist": "Katy Perry",
        "last-week": "44",
        "peak-rank": "29",
        "weeks-on-board": "10"
    },
    {
        "date": "2009-04-04",
        "rank": "52",
        "song": "Untouched",
        "artist": "The Veronicas",
        "last-week": "41",
        "peak-rank": "17",
        "weeks-on-board": "17"
    },
    {
        "date": "2009-04-04",
        "rank": "53",
        "song": "Forever",
        "artist": "Rascal Flatts",
        "last-week": "",
        "peak-rank": "53",
        "weeks-on-board": "1"
    },
    {
        "date": "2009-04-04",
        "rank": "54",
        "song": "Boom Boom Pow",
        "artist": "The Black Eyed Peas",
        "last-week": "71",
        "peak-rank": "54",
        "weeks-on-board": "2"
    },
    {
        "date": "2009-04-04",
        "rank": "55",
        "song": "Stanky Legg",
        "artist": "GS Boyz",
        "last-week": "55",
        "peak-rank": "49",
        "weeks-on-board": "7"
    },
    {
        "date": "2009-04-04",
        "rank": "56",
        "song": "It's America",
        "artist": "Rodney Atkins",
        "last-week": "53",
        "peak-rank": "52",
        "weeks-on-board": "5"
    },
    {
        "date": "2009-04-04",
        "rank": "57",
        "song": "All The Above",
        "artist": "Maino Featuring T-Pain",
        "last-week": "43",
        "peak-rank": "39",
        "weeks-on-board": "4"
    },
    {
        "date": "2009-04-04",
        "rank": "58",
        "song": "Don't Think I Can't Love You",
        "artist": "Jake Owen",
        "last-week": "58",
        "peak-rank": "57",
        "weeks-on-board": "8"
    },
    {
        "date": "2009-04-04",
        "rank": "59",
        "song": "River Of Love",
        "artist": "George Strait",
        "last-week": "59",
        "peak-rank": "59",
        "weeks-on-board": "15"
    },
    {
        "date": "2009-04-04",
        "rank": "60",
        "song": "Lucky",
        "artist": "Jason Mraz & Colbie Caillat",
        "last-week": "60",
        "peak-rank": "48",
        "weeks-on-board": "11"
    },
    {
        "date": "2009-04-04",
        "rank": "61",
        "song": "Turn My Swag On",
        "artist": "Soulja Boy Tell'em",
        "last-week": "69",
        "peak-rank": "61",
        "weeks-on-board": "3"
    },
    {
        "date": "2009-04-04",
        "rank": "62",
        "song": "Home Sweet Home",
        "artist": "Carrie Underwood",
        "last-week": "21",
        "peak-rank": "21",
        "weeks-on-board": "2"
    },
    {
        "date": "2009-04-04",
        "rank": "63",
        "song": "Candle (Sick And Tired)",
        "artist": "The White Tie Affair",
        "last-week": "67",
        "peak-rank": "63",
        "weeks-on-board": "3"
    },
    {
        "date": "2009-04-04",
        "rank": "64",
        "song": "Cowgirls Don't Cry",
        "artist": "Brooks & Dunn Featuring Reba McEntire",
        "last-week": "52",
        "peak-rank": "44",
        "weeks-on-board": "19"
    },
    {
        "date": "2009-04-04",
        "rank": "65",
        "song": "Always Strapped",
        "artist": "Birdman Featuring Lil Wayne",
        "last-week": "",
        "peak-rank": "65",
        "weeks-on-board": "1"
    },
    {
        "date": "2009-04-04",
        "rank": "66",
        "song": "God Love Her",
        "artist": "Toby Keith",
        "last-week": "54",
        "peak-rank": "36",
        "weeks-on-board": "18"
    },
    {
        "date": "2009-04-04",
        "rank": "67",
        "song": "That's Not My Name",
        "artist": "The Ting Tings",
        "last-week": "64",
        "peak-rank": "64",
        "weeks-on-board": "11"
    },
    {
        "date": "2009-04-04",
        "rank": "68",
        "song": "Hoedown Throwdown",
        "artist": "Miley Cyrus",
        "last-week": "56",
        "peak-rank": "56",
        "weeks-on-board": "2"
    },
    {
        "date": "2009-04-04",
        "rank": "69",
        "song": "You Can Get It All",
        "artist": "Bow Wow Featuring Johnta Austin",
        "last-week": "76",
        "peak-rank": "69",
        "weeks-on-board": "3"
    },
    {
        "date": "2009-04-04",
        "rank": "70",
        "song": "Use Somebody",
        "artist": "Kings Of Leon",
        "last-week": "66",
        "peak-rank": "64",
        "weeks-on-board": "8"
    },
    {
        "date": "2009-04-04",
        "rank": "71",
        "song": "You Complete Me",
        "artist": "Keyshia Cole",
        "last-week": "62",
        "peak-rank": "62",
        "weeks-on-board": "7"
    },
    {
        "date": "2009-04-04",
        "rank": "72",
        "song": "Move (If You 'W'anna)",
        "artist": "Mims",
        "last-week": "65",
        "peak-rank": "61",
        "weeks-on-board": "9"
    },
    {
        "date": "2009-04-04",
        "rank": "73",
        "song": "It Happens",
        "artist": "Sugarland",
        "last-week": "74",
        "peak-rank": "73",
        "weeks-on-board": "3"
    },
    {
        "date": "2009-04-04",
        "rank": "74",
        "song": "Nothin' To Die For",
        "artist": "Tim McGraw",
        "last-week": "68",
        "peak-rank": "68",
        "weeks-on-board": "6"
    },
    {
        "date": "2009-04-04",
        "rank": "75",
        "song": "Next To You",
        "artist": "Mike Jones",
        "last-week": "77",
        "peak-rank": "75",
        "weeks-on-board": "3"
    },
    {
        "date": "2009-04-04",
        "rank": "76",
        "song": "Careless Whisper",
        "artist": "Seether",
        "last-week": "78",
        "peak-rank": "76",
        "weeks-on-board": "3"
    },
    {
        "date": "2009-04-04",
        "rank": "77",
        "song": "Magnificent",
        "artist": "Rick Ross Featuring John Legend",
        "last-week": "87",
        "peak-rank": "77",
        "weeks-on-board": "3"
    },
    {
        "date": "2009-04-04",
        "rank": "78",
        "song": "Prom Queen",
        "artist": "Lil Wayne Featuring Shanell AKA SNL",
        "last-week": "80",
        "peak-rank": "15",
        "weeks-on-board": "8"
    },
    {
        "date": "2009-04-04",
        "rank": "79",
        "song": "Down The Road",
        "artist": "Kenny Chesney With Mac McAnally",
        "last-week": "63",
        "peak-rank": "47",
        "weeks-on-board": "16"
    },
    {
        "date": "2009-04-04",
        "rank": "80",
        "song": "Beep",
        "artist": "Bobby V Featuring Yung Joc",
        "last-week": "61",
        "peak-rank": "55",
        "weeks-on-board": "12"
    },
    {
        "date": "2009-04-04",
        "rank": "81",
        "song": "I'm On A Boat",
        "artist": "The Lonely Island Featuring T-Pain",
        "last-week": "75",
        "peak-rank": "65",
        "weeks-on-board": "6"
    },
    {
        "date": "2009-04-04",
        "rank": "82",
        "song": "Lions, Tigers & Bears",
        "artist": "Jazmine Sullivan",
        "last-week": "81",
        "peak-rank": "74",
        "weeks-on-board": "7"
    },
    {
        "date": "2009-04-04",
        "rank": "83",
        "song": "Whatever It Is",
        "artist": "Zac Brown Band",
        "last-week": "94",
        "peak-rank": "83",
        "weeks-on-board": "2"
    },
    {
        "date": "2009-04-04",
        "rank": "84",
        "song": "Don't Forget",
        "artist": "Demi Lovato",
        "last-week": "",
        "peak-rank": "68",
        "weeks-on-board": "2"
    },
    {
        "date": "2009-04-04",
        "rank": "85",
        "song": "Never Ever",
        "artist": "Ciara Featuring Young Jeezy",
        "last-week": "82",
        "peak-rank": "72",
        "weeks-on-board": "5"
    },
    {
        "date": "2009-04-04",
        "rank": "86",
        "song": "Kiss A Girl",
        "artist": "Keith Urban",
        "last-week": "51",
        "peak-rank": "51",
        "weeks-on-board": "2"
    },
    {
        "date": "2009-04-04",
        "rank": "87",
        "song": "Shuttin' Detroit Down",
        "artist": "John Rich",
        "last-week": "79",
        "peak-rank": "75",
        "weeks-on-board": "4"
    },
    {
        "date": "2009-04-04",
        "rank": "88",
        "song": "If This Isn't Love",
        "artist": "Jennifer Hudson",
        "last-week": "84",
        "peak-rank": "84",
        "weeks-on-board": "4"
    },
    {
        "date": "2009-04-04",
        "rank": "89",
        "song": "She Got Her Own",
        "artist": "Ne-Yo Featuring Jamie Foxx & Fabolous",
        "last-week": "73",
        "peak-rank": "54",
        "weeks-on-board": "15"
    },
    {
        "date": "2009-04-04",
        "rank": "90",
        "song": "Just Like Me",
        "artist": "Jamie Foxx Featuring T.I.",
        "last-week": "72",
        "peak-rank": "49",
        "weeks-on-board": "15"
    },
    {
        "date": "2009-04-04",
        "rank": "91",
        "song": "Boyfriend #2",
        "artist": "Pleasure P",
        "last-week": "",
        "peak-rank": "91",
        "weeks-on-board": "1"
    },
    {
        "date": "2009-04-04",
        "rank": "92",
        "song": "sobeautiful",
        "artist": "Musiq Soulchild",
        "last-week": "98",
        "peak-rank": "92",
        "weeks-on-board": "2"
    },
    {
        "date": "2009-04-04",
        "rank": "93",
        "song": "Ride",
        "artist": "Martina McBride",
        "last-week": "88",
        "peak-rank": "88",
        "weeks-on-board": "4"
    },
    {
        "date": "2009-04-04",
        "rank": "94",
        "song": "I'm In",
        "artist": "Keith Urban",
        "last-week": "",
        "peak-rank": "94",
        "weeks-on-board": "1"
    },
    {
        "date": "2009-04-04",
        "rank": "95",
        "song": "You're Not Sorry",
        "artist": "Taylor Swift",
        "last-week": "40",
        "peak-rank": "11",
        "weeks-on-board": "5"
    },
    {
        "date": "2009-04-04",
        "rank": "96",
        "song": "Lost",
        "artist": "Gorilla Zoe",
        "last-week": "95",
        "peak-rank": "71",
        "weeks-on-board": "11"
    },
    {
        "date": "2009-04-04",
        "rank": "97",
        "song": "Always The Love Songs",
        "artist": "Eli Young Band",
        "last-week": "",
        "peak-rank": "97",
        "weeks-on-board": "1"
    },
    {
        "date": "2009-04-04",
        "rank": "98",
        "song": "One In Every Crowd",
        "artist": "Montgomery Gentry",
        "last-week": "100",
        "peak-rank": "98",
        "weeks-on-board": "2"
    },
    {
        "date": "2009-04-04",
        "rank": "99",
        "song": "Kids",
        "artist": "MGMT",
        "last-week": "92",
        "peak-rank": "91",
        "weeks-on-board": "3"
    },
    {
        "date": "2009-04-04",
        "rank": "100",
        "song": "I Run To You",
        "artist": "Lady Antebellum",
        "last-week": "",
        "peak-rank": "100",
        "weeks-on-board": "1"
    }
]