[
    {
        "date": "1978-09-16",
        "rank": "1",
        "song": "Boogie Oogie Oogie",
        "artist": "A Taste Of Honey",
        "last-week": "1",
        "peak-rank": "1",
        "weeks-on-board": "13"
    },
    {
        "date": "1978-09-16",
        "rank": "2",
        "song": "Three Times A Lady",
        "artist": "Commodores",
        "last-week": "2",
        "peak-rank": "1",
        "weeks-on-board": "14"
    },
    {
        "date": "1978-09-16",
        "rank": "3",
        "song": "Hot Blooded",
        "artist": "Foreigner",
        "last-week": "3",
        "peak-rank": "3",
        "weeks-on-board": "12"
    },
    {
        "date": "1978-09-16",
        "rank": "4",
        "song": "Hopelessly Devoted To You",
        "artist": "Olivia Newton-John",
        "last-week": "4",
        "peak-rank": "4",
        "weeks-on-board": "11"
    },
    {
        "date": "1978-09-16",
        "rank": "5",
        "song": "Kiss You All Over",
        "artist": "Exile",
        "last-week": "5",
        "peak-rank": "5",
        "weeks-on-board": "11"
    },
    {
        "date": "1978-09-16",
        "rank": "6",
        "song": "An Everlasting Love",
        "artist": "Andy Gibb",
        "last-week": "7",
        "peak-rank": "6",
        "weeks-on-board": "10"
    },
    {
        "date": "1978-09-16",
        "rank": "7",
        "song": "Summer Nights",
        "artist": "John Travolta & Olivia Newton-John & Cast",
        "last-week": "8",
        "peak-rank": "7",
        "weeks-on-board": "7"
    },
    {
        "date": "1978-09-16",
        "rank": "8",
        "song": "Don't Look Back",
        "artist": "Boston",
        "last-week": "12",
        "peak-rank": "8",
        "weeks-on-board": "5"
    },
    {
        "date": "1978-09-16",
        "rank": "9",
        "song": "Got To Get You Into My Life",
        "artist": "Earth, Wind & Fire",
        "last-week": "10",
        "peak-rank": "9",
        "weeks-on-board": "9"
    },
    {
        "date": "1978-09-16",
        "rank": "10",
        "song": "Shame",
        "artist": "Evelyn \"Champagne\" King",
        "last-week": "9",
        "peak-rank": "9",
        "weeks-on-board": "14"
    },
    {
        "date": "1978-09-16",
        "rank": "11",
        "song": "Hot Child In The City",
        "artist": "Nick Gilder",
        "last-week": "11",
        "peak-rank": "11",
        "weeks-on-board": "15"
    },
    {
        "date": "1978-09-16",
        "rank": "12",
        "song": "Fool If You Think It's Over",
        "artist": "Chris Rea",
        "last-week": "13",
        "peak-rank": "12",
        "weeks-on-board": "11"
    },
    {
        "date": "1978-09-16",
        "rank": "13",
        "song": "Love Is In The Air",
        "artist": "John Paul Young",
        "last-week": "14",
        "peak-rank": "13",
        "weeks-on-board": "10"
    },
    {
        "date": "1978-09-16",
        "rank": "14",
        "song": "You And I",
        "artist": "Rick James",
        "last-week": "16",
        "peak-rank": "14",
        "weeks-on-board": "12"
    },
    {
        "date": "1978-09-16",
        "rank": "15",
        "song": "Reminiscing",
        "artist": "Little River Band",
        "last-week": "17",
        "peak-rank": "15",
        "weeks-on-board": "8"
    },
    {
        "date": "1978-09-16",
        "rank": "16",
        "song": "You Needed Me",
        "artist": "Anne Murray",
        "last-week": "18",
        "peak-rank": "16",
        "weeks-on-board": "10"
    },
    {
        "date": "1978-09-16",
        "rank": "17",
        "song": "Hollywood Nights",
        "artist": "Bob Seger & The Silver Bullet Band",
        "last-week": "19",
        "peak-rank": "17",
        "weeks-on-board": "6"
    },
    {
        "date": "1978-09-16",
        "rank": "18",
        "song": "Grease",
        "artist": "Frankie Valli",
        "last-week": "6",
        "peak-rank": "1",
        "weeks-on-board": "17"
    },
    {
        "date": "1978-09-16",
        "rank": "19",
        "song": "Whenever I Call You \"Friend\"",
        "artist": "Kenny Loggins",
        "last-week": "23",
        "peak-rank": "19",
        "weeks-on-board": "8"
    },
    {
        "date": "1978-09-16",
        "rank": "20",
        "song": "Miss You",
        "artist": "The Rolling Stones",
        "last-week": "15",
        "peak-rank": "1",
        "weeks-on-board": "17"
    },
    {
        "date": "1978-09-16",
        "rank": "21",
        "song": "Oh! Darling",
        "artist": "Robin Gibb",
        "last-week": "24",
        "peak-rank": "21",
        "weeks-on-board": "6"
    },
    {
        "date": "1978-09-16",
        "rank": "22",
        "song": "Magnet And Steel",
        "artist": "Walter Egan",
        "last-week": "20",
        "peak-rank": "8",
        "weeks-on-board": "17"
    },
    {
        "date": "1978-09-16",
        "rank": "23",
        "song": "Love Theme From \"Eyes Of Laura Mars\" (Prisoner)",
        "artist": "Barbra Streisand",
        "last-week": "25",
        "peak-rank": "23",
        "weeks-on-board": "8"
    },
    {
        "date": "1978-09-16",
        "rank": "24",
        "song": "Right Down The Line",
        "artist": "Gerry Rafferty",
        "last-week": "29",
        "peak-rank": "24",
        "weeks-on-board": "6"
    },
    {
        "date": "1978-09-16",
        "rank": "25",
        "song": "Close The Door",
        "artist": "Teddy Pendergrass",
        "last-week": "26",
        "peak-rank": "25",
        "weeks-on-board": "11"
    },
    {
        "date": "1978-09-16",
        "rank": "26",
        "song": "Back In The U.s.a.",
        "artist": "Linda Ronstadt",
        "last-week": "30",
        "peak-rank": "26",
        "weeks-on-board": "5"
    },
    {
        "date": "1978-09-16",
        "rank": "27",
        "song": "Just What I Needed",
        "artist": "The Cars",
        "last-week": "28",
        "peak-rank": "27",
        "weeks-on-board": "14"
    },
    {
        "date": "1978-09-16",
        "rank": "28",
        "song": "Get Off",
        "artist": "Foxy",
        "last-week": "32",
        "peak-rank": "28",
        "weeks-on-board": "9"
    },
    {
        "date": "1978-09-16",
        "rank": "29",
        "song": "Come Together",
        "artist": "Aerosmith",
        "last-week": "33",
        "peak-rank": "29",
        "weeks-on-board": "7"
    },
    {
        "date": "1978-09-16",
        "rank": "30",
        "song": "A Rock 'N' Roll Fantasy",
        "artist": "The Kinks",
        "last-week": "31",
        "peak-rank": "30",
        "weeks-on-board": "9"
    },
    {
        "date": "1978-09-16",
        "rank": "31",
        "song": "She's Always A Woman",
        "artist": "Billy Joel",
        "last-week": "35",
        "peak-rank": "31",
        "weeks-on-board": "6"
    },
    {
        "date": "1978-09-16",
        "rank": "32",
        "song": "You Never Done It Like That",
        "artist": "Captain & Tennille",
        "last-week": "36",
        "peak-rank": "32",
        "weeks-on-board": "7"
    },
    {
        "date": "1978-09-16",
        "rank": "33",
        "song": "I Love The Nightlife (Disco 'round)",
        "artist": "Alicia Bridges",
        "last-week": "37",
        "peak-rank": "33",
        "weeks-on-board": "11"
    },
    {
        "date": "1978-09-16",
        "rank": "34",
        "song": "Talking In Your Sleep",
        "artist": "Crystal Gayle",
        "last-week": "38",
        "peak-rank": "34",
        "weeks-on-board": "8"
    },
    {
        "date": "1978-09-16",
        "rank": "35",
        "song": "Who Are You",
        "artist": "The Who",
        "last-week": "41",
        "peak-rank": "35",
        "weeks-on-board": "4"
    },
    {
        "date": "1978-09-16",
        "rank": "36",
        "song": "5.7.0.5.",
        "artist": "City Boy",
        "last-week": "40",
        "peak-rank": "36",
        "weeks-on-board": "6"
    },
    {
        "date": "1978-09-16",
        "rank": "37",
        "song": "Love Will Find A Way",
        "artist": "Pablo Cruise",
        "last-week": "21",
        "peak-rank": "6",
        "weeks-on-board": "16"
    },
    {
        "date": "1978-09-16",
        "rank": "38",
        "song": "Two Tickets To Paradise",
        "artist": "Eddie Money",
        "last-week": "22",
        "peak-rank": "22",
        "weeks-on-board": "13"
    },
    {
        "date": "1978-09-16",
        "rank": "39",
        "song": "My Angel Baby",
        "artist": "Toby Beau",
        "last-week": "27",
        "peak-rank": "13",
        "weeks-on-board": "16"
    },
    {
        "date": "1978-09-16",
        "rank": "40",
        "song": "Paradise By The Dashboard Light",
        "artist": "Meat Loaf",
        "last-week": "42",
        "peak-rank": "40",
        "weeks-on-board": "6"
    },
    {
        "date": "1978-09-16",
        "rank": "41",
        "song": "Almost Like Being In Love",
        "artist": "Michael Johnson",
        "last-week": "43",
        "peak-rank": "41",
        "weeks-on-board": "6"
    },
    {
        "date": "1978-09-16",
        "rank": "42",
        "song": "Devoted To You",
        "artist": "Carly Simon & James Taylor",
        "last-week": "45",
        "peak-rank": "42",
        "weeks-on-board": "5"
    },
    {
        "date": "1978-09-16",
        "rank": "43",
        "song": "All I See Is Your Face",
        "artist": "Dan Hill",
        "last-week": "47",
        "peak-rank": "43",
        "weeks-on-board": "6"
    },
    {
        "date": "1978-09-16",
        "rank": "44",
        "song": "I Will Still Love You",
        "artist": "Stonebolt",
        "last-week": "44",
        "peak-rank": "44",
        "weeks-on-board": "7"
    },
    {
        "date": "1978-09-16",
        "rank": "45",
        "song": "Badlands",
        "artist": "Bruce Springsteen",
        "last-week": "50",
        "peak-rank": "45",
        "weeks-on-board": "5"
    },
    {
        "date": "1978-09-16",
        "rank": "46",
        "song": "You",
        "artist": "The McCrarys",
        "last-week": "55",
        "peak-rank": "46",
        "weeks-on-board": "5"
    },
    {
        "date": "1978-09-16",
        "rank": "47",
        "song": "Dance (Disco Heat)",
        "artist": "Sylvester",
        "last-week": "51",
        "peak-rank": "47",
        "weeks-on-board": "5"
    },
    {
        "date": "1978-09-16",
        "rank": "48",
        "song": "Heartbreaker",
        "artist": "Dolly Parton",
        "last-week": "58",
        "peak-rank": "48",
        "weeks-on-board": "4"
    },
    {
        "date": "1978-09-16",
        "rank": "49",
        "song": "Josie",
        "artist": "Steely Dan",
        "last-week": "56",
        "peak-rank": "49",
        "weeks-on-board": "4"
    },
    {
        "date": "1978-09-16",
        "rank": "50",
        "song": "Took The Last Train",
        "artist": "David Gates",
        "last-week": "57",
        "peak-rank": "50",
        "weeks-on-board": "6"
    },
    {
        "date": "1978-09-16",
        "rank": "51",
        "song": "It's A Laugh",
        "artist": "Daryl Hall John Oates",
        "last-week": "62",
        "peak-rank": "51",
        "weeks-on-board": "4"
    },
    {
        "date": "1978-09-16",
        "rank": "52",
        "song": "Beast Of Burden",
        "artist": "The Rolling Stones",
        "last-week": "70",
        "peak-rank": "52",
        "weeks-on-board": "2"
    },
    {
        "date": "1978-09-16",
        "rank": "53",
        "song": "Holding On (When Love Is Gone)",
        "artist": "L.T.D.",
        "last-week": "60",
        "peak-rank": "53",
        "weeks-on-board": "5"
    },
    {
        "date": "1978-09-16",
        "rank": "54",
        "song": "She Loves To Be In Love",
        "artist": "Charlie",
        "last-week": "54",
        "peak-rank": "54",
        "weeks-on-board": "7"
    },
    {
        "date": "1978-09-16",
        "rank": "55",
        "song": "Last Dance",
        "artist": "Donna Summer",
        "last-week": "46",
        "peak-rank": "3",
        "weeks-on-board": "19"
    },
    {
        "date": "1978-09-16",
        "rank": "56",
        "song": "Sweet Life",
        "artist": "Paul Davis",
        "last-week": "63",
        "peak-rank": "56",
        "weeks-on-board": "4"
    },
    {
        "date": "1978-09-16",
        "rank": "57",
        "song": "Livingston Saturday Night",
        "artist": "Jimmy Buffett",
        "last-week": "52",
        "peak-rank": "52",
        "weeks-on-board": "6"
    },
    {
        "date": "1978-09-16",
        "rank": "58",
        "song": "Think It Over",
        "artist": "Cheryl Ladd",
        "last-week": "34",
        "peak-rank": "34",
        "weeks-on-board": "9"
    },
    {
        "date": "1978-09-16",
        "rank": "59",
        "song": "Steppin' In A Slide Zone",
        "artist": "The Moody Blues",
        "last-week": "39",
        "peak-rank": "39",
        "weeks-on-board": "8"
    },
    {
        "date": "1978-09-16",
        "rank": "60",
        "song": "Stuff Like That",
        "artist": "Quincy Jones",
        "last-week": "48",
        "peak-rank": "21",
        "weeks-on-board": "15"
    },
    {
        "date": "1978-09-16",
        "rank": "61",
        "song": "If My Friends Could See Me Now",
        "artist": "Linda Clifford",
        "last-week": "71",
        "peak-rank": "61",
        "weeks-on-board": "4"
    },
    {
        "date": "1978-09-16",
        "rank": "62",
        "song": "Macho Man",
        "artist": "Village People",
        "last-week": "49",
        "peak-rank": "25",
        "weeks-on-board": "13"
    },
    {
        "date": "1978-09-16",
        "rank": "63",
        "song": "How Much I Feel",
        "artist": "Ambrosia",
        "last-week": "80",
        "peak-rank": "63",
        "weeks-on-board": "3"
    },
    {
        "date": "1978-09-16",
        "rank": "64",
        "song": "Shake And Dance With Me",
        "artist": "ConFunkShun",
        "last-week": "66",
        "peak-rank": "64",
        "weeks-on-board": "4"
    },
    {
        "date": "1978-09-16",
        "rank": "65",
        "song": "London Town",
        "artist": "Wings",
        "last-week": "75",
        "peak-rank": "65",
        "weeks-on-board": "2"
    },
    {
        "date": "1978-09-16",
        "rank": "66",
        "song": "Ease On Down The Road",
        "artist": "Diana Ross & Michael Jackson",
        "last-week": "77",
        "peak-rank": "66",
        "weeks-on-board": "2"
    },
    {
        "date": "1978-09-16",
        "rank": "67",
        "song": "Copacabana (at The Copa)",
        "artist": "Barry Manilow",
        "last-week": "53",
        "peak-rank": "8",
        "weeks-on-board": "15"
    },
    {
        "date": "1978-09-16",
        "rank": "68",
        "song": "Themes From The Wizard Of Oz",
        "artist": "Meco",
        "last-week": "78",
        "peak-rank": "68",
        "weeks-on-board": "2"
    },
    {
        "date": "1978-09-16",
        "rank": "69",
        "song": "Rivers Of Babylon",
        "artist": "Boney M.",
        "last-week": "69",
        "peak-rank": "30",
        "weeks-on-board": "16"
    },
    {
        "date": "1978-09-16",
        "rank": "70",
        "song": "Ready To Take A Chance Again",
        "artist": "Barry Manilow",
        "last-week": "",
        "peak-rank": "70",
        "weeks-on-board": "1"
    },
    {
        "date": "1978-09-16",
        "rank": "71",
        "song": "Ain't Nothing Gonna Keep Me From You",
        "artist": "Teri DeSario",
        "last-week": "73",
        "peak-rank": "43",
        "weeks-on-board": "12"
    },
    {
        "date": "1978-09-16",
        "rank": "72",
        "song": "Peggy Sue",
        "artist": "The Beach Boys",
        "last-week": "82",
        "peak-rank": "72",
        "weeks-on-board": "2"
    },
    {
        "date": "1978-09-16",
        "rank": "73",
        "song": "Blue Collar Man (Long Nights)",
        "artist": "Styx",
        "last-week": "",
        "peak-rank": "73",
        "weeks-on-board": "1"
    },
    {
        "date": "1978-09-16",
        "rank": "74",
        "song": "Crazy Feelin'",
        "artist": "Jefferson Starship",
        "last-week": "84",
        "peak-rank": "74",
        "weeks-on-board": "2"
    },
    {
        "date": "1978-09-16",
        "rank": "75",
        "song": "MacArthur Park",
        "artist": "Donna Summer",
        "last-week": "85",
        "peak-rank": "75",
        "weeks-on-board": "2"
    },
    {
        "date": "1978-09-16",
        "rank": "76",
        "song": "Prisoner Of Your Love",
        "artist": "Player",
        "last-week": "89",
        "peak-rank": "76",
        "weeks-on-board": "2"
    },
    {
        "date": "1978-09-16",
        "rank": "77",
        "song": "I Just Wanna Stop",
        "artist": "Gino Vannelli",
        "last-week": "87",
        "peak-rank": "77",
        "weeks-on-board": "2"
    },
    {
        "date": "1978-09-16",
        "rank": "78",
        "song": "Let's Get Crazy Tonight",
        "artist": "Rupert Holmes",
        "last-week": "81",
        "peak-rank": "78",
        "weeks-on-board": "3"
    },
    {
        "date": "1978-09-16",
        "rank": "79",
        "song": "Sharing The Night Together",
        "artist": "Dr. Hook",
        "last-week": "",
        "peak-rank": "79",
        "weeks-on-board": "1"
    },
    {
        "date": "1978-09-16",
        "rank": "80",
        "song": "Our Night",
        "artist": "Shaun Cassidy",
        "last-week": "90",
        "peak-rank": "80",
        "weeks-on-board": "2"
    },
    {
        "date": "1978-09-16",
        "rank": "81",
        "song": "Wavelength",
        "artist": "Van Morrison",
        "last-week": "",
        "peak-rank": "81",
        "weeks-on-board": "1"
    },
    {
        "date": "1978-09-16",
        "rank": "82",
        "song": "Everybody Needs Love",
        "artist": "Stephen Bishop",
        "last-week": "",
        "peak-rank": "82",
        "weeks-on-board": "1"
    },
    {
        "date": "1978-09-16",
        "rank": "83",
        "song": "Change Of Heart",
        "artist": "Eric Carmen",
        "last-week": "",
        "peak-rank": "83",
        "weeks-on-board": "1"
    },
    {
        "date": "1978-09-16",
        "rank": "84",
        "song": "New Orleans Ladies",
        "artist": "Louisiana's LeRoux",
        "last-week": "86",
        "peak-rank": "59",
        "weeks-on-board": "13"
    },
    {
        "date": "1978-09-16",
        "rank": "85",
        "song": "Champagne Jam",
        "artist": "Atlanta Rhythm Section",
        "last-week": "",
        "peak-rank": "85",
        "weeks-on-board": "1"
    },
    {
        "date": "1978-09-16",
        "rank": "86",
        "song": "In For The Night",
        "artist": "The Dirt Band",
        "last-week": "88",
        "peak-rank": "86",
        "weeks-on-board": "3"
    },
    {
        "date": "1978-09-16",
        "rank": "87",
        "song": "Sgt. Pepper's Lonely Hearts Club Band/With A Little Help From My Friends",
        "artist": "The Beatles",
        "last-week": "",
        "peak-rank": "87",
        "weeks-on-board": "1"
    },
    {
        "date": "1978-09-16",
        "rank": "88",
        "song": "Don't Want To Live Without It",
        "artist": "Pablo Cruise",
        "last-week": "",
        "peak-rank": "88",
        "weeks-on-board": "1"
    },
    {
        "date": "1978-09-16",
        "rank": "89",
        "song": "Substitute",
        "artist": "Clout",
        "last-week": "91",
        "peak-rank": "89",
        "weeks-on-board": "3"
    },
    {
        "date": "1978-09-16",
        "rank": "90",
        "song": "One Nation Under A Groove - Part I",
        "artist": "Funkadelic",
        "last-week": "",
        "peak-rank": "90",
        "weeks-on-board": "1"
    },
    {
        "date": "1978-09-16",
        "rank": "91",
        "song": "Hot Shot",
        "artist": "Karen Young",
        "last-week": "",
        "peak-rank": "91",
        "weeks-on-board": "1"
    },
    {
        "date": "1978-09-16",
        "rank": "92",
        "song": "New York City",
        "artist": "Zwol",
        "last-week": "",
        "peak-rank": "92",
        "weeks-on-board": "1"
    },
    {
        "date": "1978-09-16",
        "rank": "93",
        "song": "You're All I Need To Get By",
        "artist": "Johnny Mathis & Deniece Williams",
        "last-week": "61",
        "peak-rank": "47",
        "weeks-on-board": "8"
    },
    {
        "date": "1978-09-16",
        "rank": "94",
        "song": "Takin' It Easy",
        "artist": "Seals & Crofts",
        "last-week": "79",
        "peak-rank": "79",
        "weeks-on-board": "3"
    },
    {
        "date": "1978-09-16",
        "rank": "95",
        "song": "Raise A Little Hell",
        "artist": "Trooper",
        "last-week": "59",
        "peak-rank": "59",
        "weeks-on-board": "7"
    },
    {
        "date": "1978-09-16",
        "rank": "96",
        "song": "You",
        "artist": "Rita Coolidge",
        "last-week": "64",
        "peak-rank": "25",
        "weeks-on-board": "12"
    },
    {
        "date": "1978-09-16",
        "rank": "97",
        "song": "Life's Been Good",
        "artist": "Joe Walsh",
        "last-week": "65",
        "peak-rank": "12",
        "weeks-on-board": "15"
    },
    {
        "date": "1978-09-16",
        "rank": "98",
        "song": "Shadow Dancing",
        "artist": "Andy Gibb",
        "last-week": "67",
        "peak-rank": "1",
        "weeks-on-board": "23"
    },
    {
        "date": "1978-09-16",
        "rank": "99",
        "song": "Lights",
        "artist": "Journey",
        "last-week": "68",
        "peak-rank": "68",
        "weeks-on-board": "5"
    },
    {
        "date": "1978-09-16",
        "rank": "100",
        "song": "Stay/The Load-Out",
        "artist": "Jackson Browne",
        "last-week": "72",
        "peak-rank": "20",
        "weeks-on-board": "15"
    }
]