[
    {
        "date": "2017-02-18",
        "rank": "1",
        "song": "Shape Of You",
        "artist": "Ed Sheeran",
        "last-week": "2",
        "peak-rank": "1",
        "weeks-on-board": "4"
    },
    {
        "date": "2017-02-18",
        "rank": "2",
        "song": "Bad And Boujee",
        "artist": "Migos Featuring Lil Uzi Vert",
        "last-week": "1",
        "peak-rank": "1",
        "weeks-on-board": "12"
    },
    {
        "date": "2017-02-18",
        "rank": "3",
        "song": "I Don't Wanna Live Forever (Fifty Shades Darker)",
        "artist": "Zayn / Taylor Swift",
        "last-week": "5",
        "peak-rank": "3",
        "weeks-on-board": "8"
    },
    {
        "date": "2017-02-18",
        "rank": "4",
        "song": "Bad Things",
        "artist": "Machine Gun Kelly x Camila Cabello",
        "last-week": "4",
        "peak-rank": "4",
        "weeks-on-board": "14"
    },
    {
        "date": "2017-02-18",
        "rank": "5",
        "song": "Closer",
        "artist": "The Chainsmokers Featuring Halsey",
        "last-week": "3",
        "peak-rank": "1",
        "weeks-on-board": "27"
    },
    {
        "date": "2017-02-18",
        "rank": "6",
        "song": "Don't Wanna Know",
        "artist": "Maroon 5 Featuring Kendrick Lamar",
        "last-week": "7",
        "peak-rank": "6",
        "weeks-on-board": "17"
    },
    {
        "date": "2017-02-18",
        "rank": "7",
        "song": "Starboy",
        "artist": "The Weeknd Featuring Daft Punk",
        "last-week": "8",
        "peak-rank": "1",
        "weeks-on-board": "20"
    },
    {
        "date": "2017-02-18",
        "rank": "8",
        "song": "Fake Love",
        "artist": "Drake",
        "last-week": "9",
        "peak-rank": "8",
        "weeks-on-board": "15"
    },
    {
        "date": "2017-02-18",
        "rank": "9",
        "song": "Black Beatles",
        "artist": "Rae Sremmurd Featuring Gucci Mane",
        "last-week": "6",
        "peak-rank": "1",
        "weeks-on-board": "21"
    },
    {
        "date": "2017-02-18",
        "rank": "10",
        "song": "Scars To Your Beautiful",
        "artist": "Alessia Cara",
        "last-week": "10",
        "peak-rank": "10",
        "weeks-on-board": "23"
    },
    {
        "date": "2017-02-18",
        "rank": "11",
        "song": "Paris",
        "artist": "The Chainsmokers",
        "last-week": "13",
        "peak-rank": "7",
        "weeks-on-board": "3"
    },
    {
        "date": "2017-02-18",
        "rank": "12",
        "song": "24K Magic",
        "artist": "Bruno Mars",
        "last-week": "11",
        "peak-rank": "4",
        "weeks-on-board": "17"
    },
    {
        "date": "2017-02-18",
        "rank": "13",
        "song": "Side To Side",
        "artist": "Ariana Grande Featuring Nicki Minaj",
        "last-week": "12",
        "peak-rank": "4",
        "weeks-on-board": "23"
    },
    {
        "date": "2017-02-18",
        "rank": "14",
        "song": "Love On The Brain",
        "artist": "Rihanna",
        "last-week": "14",
        "peak-rank": "14",
        "weeks-on-board": "16"
    },
    {
        "date": "2017-02-18",
        "rank": "15",
        "song": "Bounce Back",
        "artist": "Big Sean",
        "last-week": "15",
        "peak-rank": "15",
        "weeks-on-board": "13"
    },
    {
        "date": "2017-02-18",
        "rank": "16",
        "song": "I Feel It Coming",
        "artist": "The Weeknd Featuring Daft Punk",
        "last-week": "18",
        "peak-rank": "16",
        "weeks-on-board": "11"
    },
    {
        "date": "2017-02-18",
        "rank": "17",
        "song": "Caroline",
        "artist": "Amine",
        "last-week": "17",
        "peak-rank": "11",
        "weeks-on-board": "22"
    },
    {
        "date": "2017-02-18",
        "rank": "18",
        "song": "Let Me Love You",
        "artist": "DJ Snake Featuring Justin Bieber",
        "last-week": "16",
        "peak-rank": "4",
        "weeks-on-board": "26"
    },
    {
        "date": "2017-02-18",
        "rank": "19",
        "song": "T-Shirt",
        "artist": "Migos",
        "last-week": "37",
        "peak-rank": "19",
        "weeks-on-board": "3"
    },
    {
        "date": "2017-02-18",
        "rank": "20",
        "song": "All Time Low",
        "artist": "Jon Bellion",
        "last-week": "19",
        "peak-rank": "16",
        "weeks-on-board": "17"
    },
    {
        "date": "2017-02-18",
        "rank": "21",
        "song": "Mercy",
        "artist": "Shawn Mendes",
        "last-week": "21",
        "peak-rank": "17",
        "weeks-on-board": "20"
    },
    {
        "date": "2017-02-18",
        "rank": "22",
        "song": "Can't Stop The Feeling!",
        "artist": "Justin Timberlake",
        "last-week": "23",
        "peak-rank": "1",
        "weeks-on-board": "39"
    },
    {
        "date": "2017-02-18",
        "rank": "23",
        "song": "Heathens",
        "artist": "twenty one pilots",
        "last-week": "22",
        "peak-rank": "2",
        "weeks-on-board": "33"
    },
    {
        "date": "2017-02-18",
        "rank": "24",
        "song": "Rockabye",
        "artist": "Clean Bandit Featuring Sean Paul & Anne-Marie",
        "last-week": "32",
        "peak-rank": "24",
        "weeks-on-board": "9"
    },
    {
        "date": "2017-02-18",
        "rank": "25",
        "song": "This Town",
        "artist": "Niall Horan",
        "last-week": "24",
        "peak-rank": "20",
        "weeks-on-board": "19"
    },
    {
        "date": "2017-02-18",
        "rank": "26",
        "song": "Starving",
        "artist": "Hailee Steinfeld & Grey Featuring Zedd",
        "last-week": "20",
        "peak-rank": "12",
        "weeks-on-board": "27"
    },
    {
        "date": "2017-02-18",
        "rank": "27",
        "song": "iSpy",
        "artist": "KYLE Featuring Lil Yachty",
        "last-week": "29",
        "peak-rank": "27",
        "weeks-on-board": "6"
    },
    {
        "date": "2017-02-18",
        "rank": "28",
        "song": "Water Under The Bridge",
        "artist": "Adele",
        "last-week": "26",
        "peak-rank": "26",
        "weeks-on-board": "13"
    },
    {
        "date": "2017-02-18",
        "rank": "29",
        "song": "Say You Won't Let Go",
        "artist": "James Arthur",
        "last-week": "31",
        "peak-rank": "29",
        "weeks-on-board": "15"
    },
    {
        "date": "2017-02-18",
        "rank": "30",
        "song": "Cheap Thrills",
        "artist": "Sia Featuring Sean Paul",
        "last-week": "27",
        "peak-rank": "1",
        "weeks-on-board": "51"
    },
    {
        "date": "2017-02-18",
        "rank": "31",
        "song": "Broccoli",
        "artist": "D.R.A.M. Featuring Lil Yachty",
        "last-week": "25",
        "peak-rank": "5",
        "weeks-on-board": "34"
    },
    {
        "date": "2017-02-18",
        "rank": "32",
        "song": "Treat You Better",
        "artist": "Shawn Mendes",
        "last-week": "28",
        "peak-rank": "6",
        "weeks-on-board": "35"
    },
    {
        "date": "2017-02-18",
        "rank": "33",
        "song": "Juju On That Beat (TZ Anthem)",
        "artist": "Zay Hilfigerrr & Zayion McCall",
        "last-week": "30",
        "peak-rank": "5",
        "weeks-on-board": "19"
    },
    {
        "date": "2017-02-18",
        "rank": "34",
        "song": "Better Man",
        "artist": "Little Big Town",
        "last-week": "35",
        "peak-rank": "34",
        "weeks-on-board": "14"
    },
    {
        "date": "2017-02-18",
        "rank": "35",
        "song": "Love Me Now",
        "artist": "John Legend",
        "last-week": "33",
        "peak-rank": "23",
        "weeks-on-board": "15"
    },
    {
        "date": "2017-02-18",
        "rank": "36",
        "song": "Don't Let Me Down",
        "artist": "The Chainsmokers Featuring Daya",
        "last-week": "34",
        "peak-rank": "3",
        "weeks-on-board": "51"
    },
    {
        "date": "2017-02-18",
        "rank": "37",
        "song": "Down",
        "artist": "Marian Hill",
        "last-week": "52",
        "peak-rank": "37",
        "weeks-on-board": "3"
    },
    {
        "date": "2017-02-18",
        "rank": "38",
        "song": "Body Like A Back Road",
        "artist": "Sam Hunt",
        "last-week": "",
        "peak-rank": "38",
        "weeks-on-board": "1"
    },
    {
        "date": "2017-02-18",
        "rank": "39",
        "song": "Congratulations",
        "artist": "Post Malone Featuring Quavo",
        "last-week": "58",
        "peak-rank": "39",
        "weeks-on-board": "6"
    },
    {
        "date": "2017-02-18",
        "rank": "40",
        "song": "The Greatest",
        "artist": "Sia Featuring Kendrick Lamar",
        "last-week": "38",
        "peak-rank": "18",
        "weeks-on-board": "22"
    },
    {
        "date": "2017-02-18",
        "rank": "41",
        "song": "Play That Song",
        "artist": "Train",
        "last-week": "60",
        "peak-rank": "41",
        "weeks-on-board": "10"
    },
    {
        "date": "2017-02-18",
        "rank": "42",
        "song": "Blue Ain't Your Color",
        "artist": "Keith Urban",
        "last-week": "36",
        "peak-rank": "24",
        "weeks-on-board": "21"
    },
    {
        "date": "2017-02-18",
        "rank": "43",
        "song": "Dirt On My Boots",
        "artist": "Jon Pardi",
        "last-week": "44",
        "peak-rank": "43",
        "weeks-on-board": "9"
    },
    {
        "date": "2017-02-18",
        "rank": "44",
        "song": "Party",
        "artist": "Chris Brown Featuring Usher & Gucci Mane",
        "last-week": "40",
        "peak-rank": "40",
        "weeks-on-board": "7"
    },
    {
        "date": "2017-02-18",
        "rank": "45",
        "song": "Star Of The Show",
        "artist": "Thomas Rhett",
        "last-week": "45",
        "peak-rank": "45",
        "weeks-on-board": "14"
    },
    {
        "date": "2017-02-18",
        "rank": "46",
        "song": "Make Me (Cry)",
        "artist": "Noah Cyrus Featuring Labrinth",
        "last-week": "57",
        "peak-rank": "46",
        "weeks-on-board": "8"
    },
    {
        "date": "2017-02-18",
        "rank": "47",
        "song": "Deja Vu",
        "artist": "J. Cole",
        "last-week": "46",
        "peak-rank": "7",
        "weeks-on-board": "8"
    },
    {
        "date": "2017-02-18",
        "rank": "48",
        "song": "Slippery",
        "artist": "Migos Featuring Gucci Mane",
        "last-week": "",
        "peak-rank": "48",
        "weeks-on-board": "1"
    },
    {
        "date": "2017-02-18",
        "rank": "49",
        "song": "X",
        "artist": "21 Savage & Metro Boomin Featuring Future",
        "last-week": "41",
        "peak-rank": "36",
        "weeks-on-board": "21"
    },
    {
        "date": "2017-02-18",
        "rank": "50",
        "song": "Castle On The Hill",
        "artist": "Ed Sheeran",
        "last-week": "39",
        "peak-rank": "6",
        "weeks-on-board": "4"
    },
    {
        "date": "2017-02-18",
        "rank": "51",
        "song": "Both",
        "artist": "Gucci Mane Featuring Drake",
        "last-week": "49",
        "peak-rank": "41",
        "weeks-on-board": "7"
    },
    {
        "date": "2017-02-18",
        "rank": "52",
        "song": "A Guy With A Girl",
        "artist": "Blake Shelton",
        "last-week": "42",
        "peak-rank": "42",
        "weeks-on-board": "12"
    },
    {
        "date": "2017-02-18",
        "rank": "53",
        "song": "HandClap",
        "artist": "Fitz And The Tantrums",
        "last-week": "53",
        "peak-rank": "53",
        "weeks-on-board": "19"
    },
    {
        "date": "2017-02-18",
        "rank": "54",
        "song": "Used To This",
        "artist": "Future Featuring Drake",
        "last-week": "47",
        "peak-rank": "14",
        "weeks-on-board": "13"
    },
    {
        "date": "2017-02-18",
        "rank": "55",
        "song": "Party Monster",
        "artist": "The Weeknd",
        "last-week": "50",
        "peak-rank": "16",
        "weeks-on-board": "11"
    },
    {
        "date": "2017-02-18",
        "rank": "56",
        "song": "Seein' Red",
        "artist": "Dustin Lynch",
        "last-week": "55",
        "peak-rank": "55",
        "weeks-on-board": "6"
    },
    {
        "date": "2017-02-18",
        "rank": "57",
        "song": "That's What I Like",
        "artist": "Bruno Mars",
        "last-week": "82",
        "peak-rank": "57",
        "weeks-on-board": "3"
    },
    {
        "date": "2017-02-18",
        "rank": "58",
        "song": "Kelly Price",
        "artist": "Migos Featuring Travis Scott",
        "last-week": "",
        "peak-rank": "58",
        "weeks-on-board": "1"
    },
    {
        "date": "2017-02-18",
        "rank": "59",
        "song": "I Got You",
        "artist": "Bebe Rexha",
        "last-week": "56",
        "peak-rank": "53",
        "weeks-on-board": "5"
    },
    {
        "date": "2017-02-18",
        "rank": "60",
        "song": "Location",
        "artist": "Khalid",
        "last-week": "64",
        "peak-rank": "60",
        "weeks-on-board": "4"
    },
    {
        "date": "2017-02-18",
        "rank": "61",
        "song": "Despacito",
        "artist": "Luis Fonsi & Daddy Yankee Featuring Justin Bieber",
        "last-week": "77",
        "peak-rank": "61",
        "weeks-on-board": "3"
    },
    {
        "date": "2017-02-18",
        "rank": "62",
        "song": "Call Casting",
        "artist": "Migos",
        "last-week": "",
        "peak-rank": "62",
        "weeks-on-board": "1"
    },
    {
        "date": "2017-02-18",
        "rank": "63",
        "song": "Way Down We Go",
        "artist": "KALEO",
        "last-week": "54",
        "peak-rank": "54",
        "weeks-on-board": "6"
    },
    {
        "date": "2017-02-18",
        "rank": "64",
        "song": "Issues",
        "artist": "Julia Michaels",
        "last-week": "87",
        "peak-rank": "64",
        "weeks-on-board": "2"
    },
    {
        "date": "2017-02-18",
        "rank": "65",
        "song": "Chantaje",
        "artist": "Shakira Featuring Maluma",
        "last-week": "59",
        "peak-rank": "51",
        "weeks-on-board": "12"
    },
    {
        "date": "2017-02-18",
        "rank": "66",
        "song": "Run Up",
        "artist": "Major Lazer Featuring PARTYNEXTDOOR & Nicki Minaj",
        "last-week": "",
        "peak-rank": "66",
        "weeks-on-board": "1"
    },
    {
        "date": "2017-02-18",
        "rank": "67",
        "song": "Goosebumps",
        "artist": "Travis Scott",
        "last-week": "51",
        "peak-rank": "51",
        "weeks-on-board": "13"
    },
    {
        "date": "2017-02-18",
        "rank": "68",
        "song": "Think A Little Less",
        "artist": "Michael Ray",
        "last-week": "62",
        "peak-rank": "62",
        "weeks-on-board": "6"
    },
    {
        "date": "2017-02-18",
        "rank": "69",
        "song": "The Weekend",
        "artist": "Brantley Gilbert",
        "last-week": "79",
        "peak-rank": "69",
        "weeks-on-board": "5"
    },
    {
        "date": "2017-02-18",
        "rank": "70",
        "song": "Sober Saturday Night",
        "artist": "Chris Young Featuring Vince Gill",
        "last-week": "63",
        "peak-rank": "63",
        "weeks-on-board": "5"
    },
    {
        "date": "2017-02-18",
        "rank": "71",
        "song": "I'm Better",
        "artist": "Missy Elliott Featuring Lamb",
        "last-week": "",
        "peak-rank": "71",
        "weeks-on-board": "1"
    },
    {
        "date": "2017-02-18",
        "rank": "72",
        "song": "Get Right Witcha",
        "artist": "Migos",
        "last-week": "",
        "peak-rank": "72",
        "weeks-on-board": "1"
    },
    {
        "date": "2017-02-18",
        "rank": "73",
        "song": "No Heart",
        "artist": "21 Savage & Metro Boomin",
        "last-week": "61",
        "peak-rank": "43",
        "weeks-on-board": "15"
    },
    {
        "date": "2017-02-18",
        "rank": "74",
        "song": "Moves",
        "artist": "Big Sean",
        "last-week": "72",
        "peak-rank": "62",
        "weeks-on-board": "6"
    },
    {
        "date": "2017-02-18",
        "rank": "75",
        "song": "How Far I'll Go",
        "artist": "Auli'i Cravalho",
        "last-week": "65",
        "peak-rank": "41",
        "weeks-on-board": "10"
    },
    {
        "date": "2017-02-18",
        "rank": "76",
        "song": "Swang",
        "artist": "Rae Sremmurd",
        "last-week": "75",
        "peak-rank": "61",
        "weeks-on-board": "7"
    },
    {
        "date": "2017-02-18",
        "rank": "77",
        "song": "How Far I'll Go",
        "artist": "Alessia Cara",
        "last-week": "68",
        "peak-rank": "56",
        "weeks-on-board": "9"
    },
    {
        "date": "2017-02-18",
        "rank": "78",
        "song": "Selfish",
        "artist": "PnB Rock",
        "last-week": "67",
        "peak-rank": "51",
        "weeks-on-board": "13"
    },
    {
        "date": "2017-02-18",
        "rank": "79",
        "song": "Kill A Word",
        "artist": "Eric Church Featuring Rhiannon Giddens",
        "last-week": "71",
        "peak-rank": "71",
        "weeks-on-board": "8"
    },
    {
        "date": "2017-02-18",
        "rank": "80",
        "song": "Road Less Traveled",
        "artist": "Lauren Alaina",
        "last-week": "86",
        "peak-rank": "80",
        "weeks-on-board": "2"
    },
    {
        "date": "2017-02-18",
        "rank": "81",
        "song": "Today",
        "artist": "Brad Paisley",
        "last-week": "74",
        "peak-rank": "70",
        "weeks-on-board": "5"
    },
    {
        "date": "2017-02-18",
        "rank": "82",
        "song": "Call On Me",
        "artist": "Starley",
        "last-week": "88",
        "peak-rank": "79",
        "weeks-on-board": "5"
    },
    {
        "date": "2017-02-18",
        "rank": "83",
        "song": "Not Nice",
        "artist": "PARTYNEXTDOOR",
        "last-week": "83",
        "peak-rank": "83",
        "weeks-on-board": "3"
    },
    {
        "date": "2017-02-18",
        "rank": "84",
        "song": "If The Boot Fits",
        "artist": "Granger Smith",
        "last-week": "80",
        "peak-rank": "80",
        "weeks-on-board": "3"
    },
    {
        "date": "2017-02-18",
        "rank": "85",
        "song": "Wanna Be That Song",
        "artist": "Brett Eldredge",
        "last-week": "69",
        "peak-rank": "46",
        "weeks-on-board": "18"
    },
    {
        "date": "2017-02-18",
        "rank": "86",
        "song": "Fast",
        "artist": "Luke Bryan",
        "last-week": "81",
        "peak-rank": "81",
        "weeks-on-board": "2"
    },
    {
        "date": "2017-02-18",
        "rank": "87",
        "song": "Guys My Age",
        "artist": "Hey Violet",
        "last-week": "84",
        "peak-rank": "84",
        "weeks-on-board": "2"
    },
    {
        "date": "2017-02-18",
        "rank": "88",
        "song": "Scared To Be Lonely",
        "artist": "Martin Garrix & Dua Lipa",
        "last-week": "",
        "peak-rank": "88",
        "weeks-on-board": "1"
    },
    {
        "date": "2017-02-18",
        "rank": "89",
        "song": "80s Mercedes",
        "artist": "Maren Morris",
        "last-week": "78",
        "peak-rank": "74",
        "weeks-on-board": "12"
    },
    {
        "date": "2017-02-18",
        "rank": "90",
        "song": "Dirty Laundry",
        "artist": "Carrie Underwood",
        "last-week": "66",
        "peak-rank": "48",
        "weeks-on-board": "16"
    },
    {
        "date": "2017-02-18",
        "rank": "91",
        "song": "Fresh Eyes",
        "artist": "Andy Grammer",
        "last-week": "70",
        "peak-rank": "59",
        "weeks-on-board": "18"
    },
    {
        "date": "2017-02-18",
        "rank": "92",
        "song": "OTW",
        "artist": "DJ Luke Nasty",
        "last-week": "73",
        "peak-rank": "71",
        "weeks-on-board": "7"
    },
    {
        "date": "2017-02-18",
        "rank": "93",
        "song": "Culture",
        "artist": "Migos Featuring DJ Khaled",
        "last-week": "",
        "peak-rank": "93",
        "weeks-on-board": "1"
    },
    {
        "date": "2017-02-18",
        "rank": "94",
        "song": "Redbone",
        "artist": "Childish Gambino",
        "last-week": "76",
        "peak-rank": "48",
        "weeks-on-board": "10"
    },
    {
        "date": "2017-02-18",
        "rank": "95",
        "song": "Any Ol' Barstool",
        "artist": "Jason Aldean",
        "last-week": "93",
        "peak-rank": "93",
        "weeks-on-board": "2"
    },
    {
        "date": "2017-02-18",
        "rank": "96",
        "song": "Sex With Me",
        "artist": "Rihanna",
        "last-week": "85",
        "peak-rank": "83",
        "weeks-on-board": "14"
    },
    {
        "date": "2017-02-18",
        "rank": "97",
        "song": "Black",
        "artist": "Dierks Bentley",
        "last-week": "90",
        "peak-rank": "90",
        "weeks-on-board": "3"
    },
    {
        "date": "2017-02-18",
        "rank": "98",
        "song": "Alone",
        "artist": "Marshmello",
        "last-week": "89",
        "peak-rank": "60",
        "weeks-on-board": "10"
    },
    {
        "date": "2017-02-18",
        "rank": "99",
        "song": "El Amante",
        "artist": "Nicky Jam",
        "last-week": "",
        "peak-rank": "99",
        "weeks-on-board": "1"
    },
    {
        "date": "2017-02-18",
        "rank": "100",
        "song": "Some Kind Of Drug",
        "artist": "G-Eazy Featuring Marc E. Bassy",
        "last-week": "",
        "peak-rank": "100",
        "weeks-on-board": "1"
    }
]