[
    {
        "date": "1960-02-15",
        "rank": "1",
        "song": "Teen Angel",
        "artist": "Mark Dinning",
        "last-week": "1",
        "peak-rank": "1",
        "weeks-on-board": "9"
    },
    {
        "date": "1960-02-15",
        "rank": "2",
        "song": "Running Bear",
        "artist": "Johnny Preston",
        "last-week": "2",
        "peak-rank": "1",
        "weeks-on-board": "18"
    },
    {
        "date": "1960-02-15",
        "rank": "3",
        "song": "Handy Man",
        "artist": "Jimmy Jones",
        "last-week": "5",
        "peak-rank": "3",
        "weeks-on-board": "8"
    },
    {
        "date": "1960-02-15",
        "rank": "4",
        "song": "He'll Have To Go",
        "artist": "Jim Reeves",
        "last-week": "8",
        "peak-rank": "4",
        "weeks-on-board": "8"
    },
    {
        "date": "1960-02-15",
        "rank": "5",
        "song": "Where Or When",
        "artist": "Dion & The Belmonts",
        "last-week": "3",
        "peak-rank": "3",
        "weeks-on-board": "8"
    },
    {
        "date": "1960-02-15",
        "rank": "6",
        "song": "The Theme From \"A Summer Place\"",
        "artist": "Percy Faith And His Orchestra",
        "last-week": "12",
        "peak-rank": "6",
        "weeks-on-board": "6"
    },
    {
        "date": "1960-02-15",
        "rank": "7",
        "song": "What In The World's Come Over You",
        "artist": "Jack Scott",
        "last-week": "7",
        "peak-rank": "7",
        "weeks-on-board": "6"
    },
    {
        "date": "1960-02-15",
        "rank": "8",
        "song": "Lonely Blue Boy",
        "artist": "Conway Twitty",
        "last-week": "6",
        "peak-rank": "6",
        "weeks-on-board": "8"
    },
    {
        "date": "1960-02-15",
        "rank": "9",
        "song": "Let It Be Me",
        "artist": "The Everly Brothers",
        "last-week": "13",
        "peak-rank": "9",
        "weeks-on-board": "6"
    },
    {
        "date": "1960-02-15",
        "rank": "10",
        "song": "El Paso",
        "artist": "Marty Robbins",
        "last-week": "4",
        "peak-rank": "1",
        "weeks-on-board": "15"
    },
    {
        "date": "1960-02-15",
        "rank": "11",
        "song": "Beyond The Sea",
        "artist": "Bobby Darin",
        "last-week": "19",
        "peak-rank": "11",
        "weeks-on-board": "5"
    },
    {
        "date": "1960-02-15",
        "rank": "12",
        "song": "Pretty Blue Eyes",
        "artist": "Steve Lawrence",
        "last-week": "14",
        "peak-rank": "9",
        "weeks-on-board": "13"
    },
    {
        "date": "1960-02-15",
        "rank": "13",
        "song": "Down By The Station",
        "artist": "The Four Preps",
        "last-week": "16",
        "peak-rank": "13",
        "weeks-on-board": "8"
    },
    {
        "date": "1960-02-15",
        "rank": "14",
        "song": "You Got What It Takes",
        "artist": "Marv Johnson",
        "last-week": "10",
        "peak-rank": "10",
        "weeks-on-board": "16"
    },
    {
        "date": "1960-02-15",
        "rank": "15",
        "song": "Go, Jimmy, Go",
        "artist": "Jimmy Clanton",
        "last-week": "11",
        "peak-rank": "5",
        "weeks-on-board": "11"
    },
    {
        "date": "1960-02-15",
        "rank": "16",
        "song": "Why",
        "artist": "Frankie Avalon",
        "last-week": "9",
        "peak-rank": "1",
        "weeks-on-board": "13"
    },
    {
        "date": "1960-02-15",
        "rank": "17",
        "song": "The Village Of St. Bernadette",
        "artist": "Andy Williams",
        "last-week": "15",
        "peak-rank": "7",
        "weeks-on-board": "10"
    },
    {
        "date": "1960-02-15",
        "rank": "18",
        "song": "The Big Hurt",
        "artist": "Miss Toni Fisher",
        "last-week": "17",
        "peak-rank": "3",
        "weeks-on-board": "14"
    },
    {
        "date": "1960-02-15",
        "rank": "19",
        "song": "Tracy's Theme",
        "artist": "Spencer Ross",
        "last-week": "20",
        "peak-rank": "19",
        "weeks-on-board": "7"
    },
    {
        "date": "1960-02-15",
        "rank": "20",
        "song": "Baby (You've Got What It Takes)",
        "artist": "Dinah Washington & Brook Benton",
        "last-week": "37",
        "peak-rank": "20",
        "weeks-on-board": "4"
    },
    {
        "date": "1960-02-15",
        "rank": "21",
        "song": "Forever",
        "artist": "The Little Dippers",
        "last-week": "27",
        "peak-rank": "21",
        "weeks-on-board": "4"
    },
    {
        "date": "1960-02-15",
        "rank": "22",
        "song": "Way Down Yonder In New Orleans",
        "artist": "Freddie Cannon",
        "last-week": "18",
        "peak-rank": "3",
        "weeks-on-board": "13"
    },
    {
        "date": "1960-02-15",
        "rank": "23",
        "song": "Wild One",
        "artist": "Bobby Rydell",
        "last-week": "29",
        "peak-rank": "23",
        "weeks-on-board": "3"
    },
    {
        "date": "1960-02-15",
        "rank": "24",
        "song": "Rockin' Little Angel",
        "artist": "Ray Smith",
        "last-week": "26",
        "peak-rank": "24",
        "weeks-on-board": "7"
    },
    {
        "date": "1960-02-15",
        "rank": "25",
        "song": "T.L.C. Tender Love And Care",
        "artist": "Jimmie Rodgers",
        "last-week": "25",
        "peak-rank": "25",
        "weeks-on-board": "6"
    },
    {
        "date": "1960-02-15",
        "rank": "26",
        "song": "Shimmy, Shimmy, Ko-Ko-Bop",
        "artist": "Little Anthony And The Imperials",
        "last-week": "24",
        "peak-rank": "24",
        "weeks-on-board": "11"
    },
    {
        "date": "1960-02-15",
        "rank": "27",
        "song": "Harbor Lights",
        "artist": "The Platters",
        "last-week": "41",
        "peak-rank": "27",
        "weeks-on-board": "4"
    },
    {
        "date": "1960-02-15",
        "rank": "28",
        "song": "Sandy",
        "artist": "Larry Hall",
        "last-week": "23",
        "peak-rank": "15",
        "weeks-on-board": "13"
    },
    {
        "date": "1960-02-15",
        "rank": "29",
        "song": "Bulldog",
        "artist": "The Fireballs",
        "last-week": "34",
        "peak-rank": "29",
        "weeks-on-board": "6"
    },
    {
        "date": "1960-02-15",
        "rank": "30",
        "song": "Sweet Nothin's",
        "artist": "Brenda Lee",
        "last-week": "42",
        "peak-rank": "30",
        "weeks-on-board": "9"
    },
    {
        "date": "1960-02-15",
        "rank": "31",
        "song": "Lucky Devil",
        "artist": "Carl Dobkins, Jr.",
        "last-week": "28",
        "peak-rank": "25",
        "weeks-on-board": "11"
    },
    {
        "date": "1960-02-15",
        "rank": "32",
        "song": "Among My Souvenirs",
        "artist": "Connie Francis",
        "last-week": "22",
        "peak-rank": "7",
        "weeks-on-board": "13"
    },
    {
        "date": "1960-02-15",
        "rank": "33",
        "song": "Midnite Special",
        "artist": "Paul Evans",
        "last-week": "45",
        "peak-rank": "33",
        "weeks-on-board": "4"
    },
    {
        "date": "1960-02-15",
        "rank": "34",
        "song": "Time And The River",
        "artist": "Nat King Cole",
        "last-week": "50",
        "peak-rank": "34",
        "weeks-on-board": "3"
    },
    {
        "date": "1960-02-15",
        "rank": "35",
        "song": "Lady Luck",
        "artist": "Lloyd Price and His Orchestra",
        "last-week": "51",
        "peak-rank": "35",
        "weeks-on-board": "3"
    },
    {
        "date": "1960-02-15",
        "rank": "36",
        "song": "Too Much Tequila",
        "artist": "The Champs",
        "last-week": "39",
        "peak-rank": "36",
        "weeks-on-board": "5"
    },
    {
        "date": "1960-02-15",
        "rank": "37",
        "song": "Country Boy",
        "artist": "Fats Domino",
        "last-week": "55",
        "peak-rank": "37",
        "weeks-on-board": "3"
    },
    {
        "date": "1960-02-15",
        "rank": "38",
        "song": "Not One Minute More",
        "artist": "Della Reese",
        "last-week": "30",
        "peak-rank": "16",
        "weeks-on-board": "10"
    },
    {
        "date": "1960-02-15",
        "rank": "39",
        "song": "It's Time To Cry",
        "artist": "Paul Anka",
        "last-week": "21",
        "peak-rank": "4",
        "weeks-on-board": "13"
    },
    {
        "date": "1960-02-15",
        "rank": "40",
        "song": "First Name Initial",
        "artist": "Annette With The Afterbeats",
        "last-week": "32",
        "peak-rank": "20",
        "weeks-on-board": "17"
    },
    {
        "date": "1960-02-15",
        "rank": "41",
        "song": "Little Bitty Girl",
        "artist": "Bobby Rydell",
        "last-week": "54",
        "peak-rank": "41",
        "weeks-on-board": "3"
    },
    {
        "date": "1960-02-15",
        "rank": "42",
        "song": "China Doll",
        "artist": "The Ames Brothers",
        "last-week": "48",
        "peak-rank": "42",
        "weeks-on-board": "3"
    },
    {
        "date": "1960-02-15",
        "rank": "43",
        "song": "Why Do I Love You So",
        "artist": "Johnny Tillotson",
        "last-week": "46",
        "peak-rank": "43",
        "weeks-on-board": "5"
    },
    {
        "date": "1960-02-15",
        "rank": "44",
        "song": "Delaware",
        "artist": "Perry Como",
        "last-week": "71",
        "peak-rank": "44",
        "weeks-on-board": "2"
    },
    {
        "date": "1960-02-15",
        "rank": "45",
        "song": "If I Had A Girl",
        "artist": "Rod Lauren",
        "last-week": "40",
        "peak-rank": "31",
        "weeks-on-board": "9"
    },
    {
        "date": "1960-02-15",
        "rank": "46",
        "song": "Little Coco Palm",
        "artist": "Jerry Wallace",
        "last-week": "38",
        "peak-rank": "36",
        "weeks-on-board": "7"
    },
    {
        "date": "1960-02-15",
        "rank": "47",
        "song": "Am I That Easy To Forget",
        "artist": "Debbie Reynolds",
        "last-week": "44",
        "peak-rank": "44",
        "weeks-on-board": "5"
    },
    {
        "date": "1960-02-15",
        "rank": "48",
        "song": "Crazy Arms",
        "artist": "Bob Beckham",
        "last-week": "58",
        "peak-rank": "48",
        "weeks-on-board": "7"
    },
    {
        "date": "1960-02-15",
        "rank": "49",
        "song": "Bonnie Came Back",
        "artist": "Duane Eddy His Twangy Guitar And The Rebels",
        "last-week": "33",
        "peak-rank": "26",
        "weeks-on-board": "8"
    },
    {
        "date": "1960-02-15",
        "rank": "50",
        "song": "(There Was A) Tall Oak Tree",
        "artist": "Dorsey Burnette",
        "last-week": "74",
        "peak-rank": "50",
        "weeks-on-board": "3"
    },
    {
        "date": "1960-02-15",
        "rank": "51",
        "song": "Hound Dog Man",
        "artist": "Fabian",
        "last-week": "31",
        "peak-rank": "9",
        "weeks-on-board": "14"
    },
    {
        "date": "1960-02-15",
        "rank": "52",
        "song": "Eternally",
        "artist": "Sarah Vaughan",
        "last-week": "61",
        "peak-rank": "52",
        "weeks-on-board": "2"
    },
    {
        "date": "1960-02-15",
        "rank": "53",
        "song": "Little Things Mean A Lot",
        "artist": "Joni James",
        "last-week": "36",
        "peak-rank": "35",
        "weeks-on-board": "8"
    },
    {
        "date": "1960-02-15",
        "rank": "54",
        "song": "Heartaches By The Number",
        "artist": "Guy Mitchell",
        "last-week": "47",
        "peak-rank": "1",
        "weeks-on-board": "20"
    },
    {
        "date": "1960-02-15",
        "rank": "55",
        "song": "Smokie - Part 2",
        "artist": "Bill Black's Combo",
        "last-week": "35",
        "peak-rank": "17",
        "weeks-on-board": "12"
    },
    {
        "date": "1960-02-15",
        "rank": "56",
        "song": "Money (That's what I want)",
        "artist": "Barrett Strong",
        "last-week": "80",
        "peak-rank": "56",
        "weeks-on-board": "3"
    },
    {
        "date": "1960-02-15",
        "rank": "57",
        "song": "That Old Feeling",
        "artist": "Kitty Kallen",
        "last-week": "60",
        "peak-rank": "57",
        "weeks-on-board": "3"
    },
    {
        "date": "1960-02-15",
        "rank": "58",
        "song": "The Happy Muleteer",
        "artist": "Ivo Robic",
        "last-week": "64",
        "peak-rank": "58",
        "weeks-on-board": "5"
    },
    {
        "date": "1960-02-15",
        "rank": "59",
        "song": "On The Beach",
        "artist": "Frank Chacksfield And His Orch.",
        "last-week": "63",
        "peak-rank": "59",
        "weeks-on-board": "4"
    },
    {
        "date": "1960-02-15",
        "rank": "60",
        "song": "Darling Lorraine",
        "artist": "The Knockouts",
        "last-week": "49",
        "peak-rank": "49",
        "weeks-on-board": "8"
    },
    {
        "date": "1960-02-15",
        "rank": "61",
        "song": "How About That",
        "artist": "Dee Clark",
        "last-week": "57",
        "peak-rank": "33",
        "weeks-on-board": "11"
    },
    {
        "date": "1960-02-15",
        "rank": "62",
        "song": "Bad Boy",
        "artist": "Marty Wilde",
        "last-week": "90",
        "peak-rank": "62",
        "weeks-on-board": "2"
    },
    {
        "date": "1960-02-15",
        "rank": "63",
        "song": "Amapola",
        "artist": "Jacky Noguez And His Orchestra",
        "last-week": "65",
        "peak-rank": "63",
        "weeks-on-board": "5"
    },
    {
        "date": "1960-02-15",
        "rank": "64",
        "song": "Fannie Mae",
        "artist": "Buster Brown",
        "last-week": "79",
        "peak-rank": "64",
        "weeks-on-board": "3"
    },
    {
        "date": "1960-02-15",
        "rank": "65",
        "song": "Harlem Nocturne",
        "artist": "The Viscounts",
        "last-week": "53",
        "peak-rank": "52",
        "weeks-on-board": "8"
    },
    {
        "date": "1960-02-15",
        "rank": "66",
        "song": "Tell Her For Me",
        "artist": "Adam Wade",
        "last-week": "68",
        "peak-rank": "66",
        "weeks-on-board": "6"
    },
    {
        "date": "1960-02-15",
        "rank": "67",
        "song": "Peace Of Mind",
        "artist": "Teresa Brewer",
        "last-week": "70",
        "peak-rank": "67",
        "weeks-on-board": "3"
    },
    {
        "date": "1960-02-15",
        "rank": "68",
        "song": "Sixteen Reasons",
        "artist": "Connie Stevens",
        "last-week": "73",
        "peak-rank": "68",
        "weeks-on-board": "3"
    },
    {
        "date": "1960-02-15",
        "rank": "69",
        "song": "Beatnik Fly",
        "artist": "Johnny And The Hurricanes",
        "last-week": "",
        "peak-rank": "69",
        "weeks-on-board": "1"
    },
    {
        "date": "1960-02-15",
        "rank": "70",
        "song": "Baciare Baciare (Kissing Kissing)",
        "artist": "Dorothy Collins",
        "last-week": "56",
        "peak-rank": "43",
        "weeks-on-board": "9"
    },
    {
        "date": "1960-02-15",
        "rank": "71",
        "song": "I Was Such A Fool (To Fall In Love With You)",
        "artist": "The Flamingos",
        "last-week": "72",
        "peak-rank": "71",
        "weeks-on-board": "3"
    },
    {
        "date": "1960-02-15",
        "rank": "72",
        "song": "Up Town",
        "artist": "Roy Orbison",
        "last-week": "75",
        "peak-rank": "72",
        "weeks-on-board": "5"
    },
    {
        "date": "1960-02-15",
        "rank": "73",
        "song": "Waltzing Matilda",
        "artist": "Jimmie Rodgers",
        "last-week": "43",
        "peak-rank": "41",
        "weeks-on-board": "5"
    },
    {
        "date": "1960-02-15",
        "rank": "74",
        "song": "Outside My Window",
        "artist": "The Fleetwoods",
        "last-week": "",
        "peak-rank": "74",
        "weeks-on-board": "1"
    },
    {
        "date": "1960-02-15",
        "rank": "75",
        "song": "Let It Rock",
        "artist": "Chuck Berry",
        "last-week": "81",
        "peak-rank": "75",
        "weeks-on-board": "3"
    },
    {
        "date": "1960-02-15",
        "rank": "76",
        "song": "Mack The Knife",
        "artist": "Bobby Darin",
        "last-week": "59",
        "peak-rank": "1",
        "weeks-on-board": "26"
    },
    {
        "date": "1960-02-15",
        "rank": "77",
        "song": "(Baby) Hully Gully",
        "artist": "The Olympics",
        "last-week": "83",
        "peak-rank": "77",
        "weeks-on-board": "3"
    },
    {
        "date": "1960-02-15",
        "rank": "78",
        "song": "Too Pooped To Pop (\"Casey\")",
        "artist": "Chuck Berry",
        "last-week": "",
        "peak-rank": "78",
        "weeks-on-board": "1"
    },
    {
        "date": "1960-02-15",
        "rank": "79",
        "song": "Teensville",
        "artist": "Chet Atkins",
        "last-week": "",
        "peak-rank": "79",
        "weeks-on-board": "1"
    },
    {
        "date": "1960-02-15",
        "rank": "80",
        "song": "Mumblin' Mosie",
        "artist": "The Johnny Otis Show",
        "last-week": "",
        "peak-rank": "80",
        "weeks-on-board": "1"
    },
    {
        "date": "1960-02-15",
        "rank": "81",
        "song": "I Know What God Is",
        "artist": "Perry Como",
        "last-week": "95",
        "peak-rank": "81",
        "weeks-on-board": "2"
    },
    {
        "date": "1960-02-15",
        "rank": "82",
        "song": "Baby What You Want Me To Do",
        "artist": "Jimmy Reed",
        "last-week": "",
        "peak-rank": "82",
        "weeks-on-board": "1"
    },
    {
        "date": "1960-02-15",
        "rank": "83",
        "song": "Forever",
        "artist": "Billy Walker",
        "last-week": "",
        "peak-rank": "83",
        "weeks-on-board": "1"
    },
    {
        "date": "1960-02-15",
        "rank": "84",
        "song": "(Do The) Mashed Potatoes (Part 1)",
        "artist": "Nat Kendrick And The Swans",
        "last-week": "",
        "peak-rank": "84",
        "weeks-on-board": "1"
    },
    {
        "date": "1960-02-15",
        "rank": "85",
        "song": "Just A Little Bit",
        "artist": "Rosco Gordon",
        "last-week": "",
        "peak-rank": "85",
        "weeks-on-board": "1"
    },
    {
        "date": "1960-02-15",
        "rank": "86",
        "song": "Skokiaan (South African Song)",
        "artist": "Bill Haley And His Comets",
        "last-week": "76",
        "peak-rank": "70",
        "weeks-on-board": "6"
    },
    {
        "date": "1960-02-15",
        "rank": "87",
        "song": "You're My Baby",
        "artist": "Sarah Vaughan",
        "last-week": "",
        "peak-rank": "87",
        "weeks-on-board": "1"
    },
    {
        "date": "1960-02-15",
        "rank": "88",
        "song": "Honey Hush",
        "artist": "Joe Turner",
        "last-week": "67",
        "peak-rank": "53",
        "weeks-on-board": "8"
    },
    {
        "date": "1960-02-15",
        "rank": "89",
        "song": "No Love Have I",
        "artist": "Webb Pierce",
        "last-week": "66",
        "peak-rank": "54",
        "weeks-on-board": "8"
    },
    {
        "date": "1960-02-15",
        "rank": "90",
        "song": "Honey Love",
        "artist": "Narvel Felts",
        "last-week": "99",
        "peak-rank": "90",
        "weeks-on-board": "2"
    },
    {
        "date": "1960-02-15",
        "rank": "91",
        "song": "I Can't Say Goodbye",
        "artist": "The Fireflies Featuring Ritchie Adams",
        "last-week": "",
        "peak-rank": "90",
        "weeks-on-board": "3"
    },
    {
        "date": "1960-02-15",
        "rank": "92",
        "song": "Cry Me A River",
        "artist": "Janice Harper",
        "last-week": "",
        "peak-rank": "91",
        "weeks-on-board": "3"
    },
    {
        "date": "1960-02-15",
        "rank": "93",
        "song": "Clementine",
        "artist": "Jan & Dean",
        "last-week": "100",
        "peak-rank": "93",
        "weeks-on-board": "2"
    },
    {
        "date": "1960-02-15",
        "rank": "94",
        "song": "This Friendly World",
        "artist": "Fabian",
        "last-week": "52",
        "peak-rank": "12",
        "weeks-on-board": "13"
    },
    {
        "date": "1960-02-15",
        "rank": "95",
        "song": "Don't Let The Sun Catch You Cryin'",
        "artist": "Ray Charles",
        "last-week": "98",
        "peak-rank": "95",
        "weeks-on-board": "2"
    },
    {
        "date": "1960-02-15",
        "rank": "96",
        "song": "Time After Time",
        "artist": "Frankie Ford",
        "last-week": "",
        "peak-rank": "87",
        "weeks-on-board": "4"
    },
    {
        "date": "1960-02-15",
        "rank": "97",
        "song": "What's Happening",
        "artist": "Wade Flemons",
        "last-week": "",
        "peak-rank": "97",
        "weeks-on-board": "1"
    },
    {
        "date": "1960-02-15",
        "rank": "98",
        "song": "If You Need Me",
        "artist": "Fats Domino",
        "last-week": "",
        "peak-rank": "98",
        "weeks-on-board": "1"
    },
    {
        "date": "1960-02-15",
        "rank": "99",
        "song": "Let The Little Girl Dance",
        "artist": "Billy Bland",
        "last-week": "",
        "peak-rank": "99",
        "weeks-on-board": "1"
    },
    {
        "date": "1960-02-15",
        "rank": "100",
        "song": "Paradise",
        "artist": "Sammy Turner",
        "last-week": "",
        "peak-rank": "100",
        "weeks-on-board": "1"
    }
]