[
    {
        "date": "1980-06-14",
        "rank": "1",
        "song": "Funkytown",
        "artist": "Lipps, Inc.",
        "last-week": "1",
        "peak-rank": "1",
        "weeks-on-board": "12"
    },
    {
        "date": "1980-06-14",
        "rank": "2",
        "song": "Coming Up (Live At Glasgow)",
        "artist": "Paul McCartney And Wings",
        "last-week": "2",
        "peak-rank": "2",
        "weeks-on-board": "8"
    },
    {
        "date": "1980-06-14",
        "rank": "3",
        "song": "Biggest Part Of Me",
        "artist": "Ambrosia",
        "last-week": "3",
        "peak-rank": "3",
        "weeks-on-board": "11"
    },
    {
        "date": "1980-06-14",
        "rank": "4",
        "song": "The Rose",
        "artist": "Bette Midler",
        "last-week": "6",
        "peak-rank": "4",
        "weeks-on-board": "13"
    },
    {
        "date": "1980-06-14",
        "rank": "5",
        "song": "Against The Wind",
        "artist": "Bob Seger",
        "last-week": "7",
        "peak-rank": "5",
        "weeks-on-board": "7"
    },
    {
        "date": "1980-06-14",
        "rank": "6",
        "song": "Call Me",
        "artist": "Blondie",
        "last-week": "5",
        "peak-rank": "1",
        "weeks-on-board": "18"
    },
    {
        "date": "1980-06-14",
        "rank": "7",
        "song": "It's Still Rock And Roll To Me",
        "artist": "Billy Joel",
        "last-week": "11",
        "peak-rank": "7",
        "weeks-on-board": "4"
    },
    {
        "date": "1980-06-14",
        "rank": "8",
        "song": "Little Jeannie",
        "artist": "Elton John",
        "last-week": "10",
        "peak-rank": "8",
        "weeks-on-board": "7"
    },
    {
        "date": "1980-06-14",
        "rank": "9",
        "song": "Cars",
        "artist": "Gary Numan",
        "last-week": "9",
        "peak-rank": "9",
        "weeks-on-board": "18"
    },
    {
        "date": "1980-06-14",
        "rank": "10",
        "song": "Steal Away",
        "artist": "Robbie Dupree",
        "last-week": "13",
        "peak-rank": "10",
        "weeks-on-board": "10"
    },
    {
        "date": "1980-06-14",
        "rank": "11",
        "song": "She's Out Of My Life",
        "artist": "Michael Jackson",
        "last-week": "12",
        "peak-rank": "11",
        "weeks-on-board": "9"
    },
    {
        "date": "1980-06-14",
        "rank": "12",
        "song": "Don't Fall In Love With A Dreamer",
        "artist": "Kenny Rogers With Kim Carnes",
        "last-week": "4",
        "peak-rank": "4",
        "weeks-on-board": "12"
    },
    {
        "date": "1980-06-14",
        "rank": "13",
        "song": "Cupid/I've Loved You For A Long Time",
        "artist": "The Spinners",
        "last-week": "15",
        "peak-rank": "13",
        "weeks-on-board": "5"
    },
    {
        "date": "1980-06-14",
        "rank": "14",
        "song": "Let's Get Serious",
        "artist": "Jermaine Jackson",
        "last-week": "18",
        "peak-rank": "14",
        "weeks-on-board": "12"
    },
    {
        "date": "1980-06-14",
        "rank": "15",
        "song": "Hurt So Bad",
        "artist": "Linda Ronstadt",
        "last-week": "8",
        "peak-rank": "8",
        "weeks-on-board": "10"
    },
    {
        "date": "1980-06-14",
        "rank": "16",
        "song": "Brass In Pocket (I'm Special)",
        "artist": "Pretenders",
        "last-week": "14",
        "peak-rank": "14",
        "weeks-on-board": "18"
    },
    {
        "date": "1980-06-14",
        "rank": "17",
        "song": "Stomp!",
        "artist": "The Brothers Johnson",
        "last-week": "17",
        "peak-rank": "7",
        "weeks-on-board": "14"
    },
    {
        "date": "1980-06-14",
        "rank": "18",
        "song": "Let Me Love You Tonight",
        "artist": "Pure Prairie League",
        "last-week": "20",
        "peak-rank": "18",
        "weeks-on-board": "6"
    },
    {
        "date": "1980-06-14",
        "rank": "19",
        "song": "Sexy Eyes",
        "artist": "Dr. Hook",
        "last-week": "16",
        "peak-rank": "5",
        "weeks-on-board": "18"
    },
    {
        "date": "1980-06-14",
        "rank": "20",
        "song": "Lost In Love",
        "artist": "Air Supply",
        "last-week": "19",
        "peak-rank": "3",
        "weeks-on-board": "19"
    },
    {
        "date": "1980-06-14",
        "rank": "21",
        "song": "Wondering Where The Lions Are",
        "artist": "Bruce Cockburn",
        "last-week": "21",
        "peak-rank": "21",
        "weeks-on-board": "13"
    },
    {
        "date": "1980-06-14",
        "rank": "22",
        "song": "Shining Star",
        "artist": "The Manhattans",
        "last-week": "27",
        "peak-rank": "22",
        "weeks-on-board": "8"
    },
    {
        "date": "1980-06-14",
        "rank": "23",
        "song": "Should've Never Let You Go",
        "artist": "Neil Sedaka & Dara Sedaka",
        "last-week": "25",
        "peak-rank": "23",
        "weeks-on-board": "12"
    },
    {
        "date": "1980-06-14",
        "rank": "24",
        "song": "Ride Like The Wind",
        "artist": "Christopher Cross",
        "last-week": "23",
        "peak-rank": "2",
        "weeks-on-board": "18"
    },
    {
        "date": "1980-06-14",
        "rank": "25",
        "song": "Breakdown Dead Ahead",
        "artist": "Boz Scaggs",
        "last-week": "22",
        "peak-rank": "15",
        "weeks-on-board": "12"
    },
    {
        "date": "1980-06-14",
        "rank": "26",
        "song": "Tired Of Toein' The Line",
        "artist": "Rocky Burnette",
        "last-week": "34",
        "peak-rank": "26",
        "weeks-on-board": "6"
    },
    {
        "date": "1980-06-14",
        "rank": "27",
        "song": "We Live For Love",
        "artist": "Pat Benatar",
        "last-week": "30",
        "peak-rank": "27",
        "weeks-on-board": "11"
    },
    {
        "date": "1980-06-14",
        "rank": "28",
        "song": "Lady",
        "artist": "The Whispers",
        "last-week": "28",
        "peak-rank": "28",
        "weeks-on-board": "9"
    },
    {
        "date": "1980-06-14",
        "rank": "29",
        "song": "One Fine Day",
        "artist": "Carole King",
        "last-week": "45",
        "peak-rank": "29",
        "weeks-on-board": "5"
    },
    {
        "date": "1980-06-14",
        "rank": "30",
        "song": "Twilight Zone/Twilight Tone",
        "artist": "The Manhattan Transfer",
        "last-week": "33",
        "peak-rank": "30",
        "weeks-on-board": "9"
    },
    {
        "date": "1980-06-14",
        "rank": "31",
        "song": "We Were Meant To Be Lovers",
        "artist": "Photoglo",
        "last-week": "32",
        "peak-rank": "31",
        "weeks-on-board": "12"
    },
    {
        "date": "1980-06-14",
        "rank": "32",
        "song": "Theme From New York, New York",
        "artist": "Frank Sinatra",
        "last-week": "35",
        "peak-rank": "32",
        "weeks-on-board": "7"
    },
    {
        "date": "1980-06-14",
        "rank": "33",
        "song": "Another Brick In The Wall (Part II)",
        "artist": "Pink Floyd",
        "last-week": "29",
        "peak-rank": "1",
        "weeks-on-board": "22"
    },
    {
        "date": "1980-06-14",
        "rank": "34",
        "song": "Two Places At The Same Time",
        "artist": "Ray Parker Jr. & Raydio",
        "last-week": "37",
        "peak-rank": "34",
        "weeks-on-board": "9"
    },
    {
        "date": "1980-06-14",
        "rank": "35",
        "song": "Answering Machine",
        "artist": "Rupert Holmes",
        "last-week": "41",
        "peak-rank": "35",
        "weeks-on-board": "7"
    },
    {
        "date": "1980-06-14",
        "rank": "36",
        "song": "Magic",
        "artist": "Olivia Newton-John",
        "last-week": "50",
        "peak-rank": "36",
        "weeks-on-board": "4"
    },
    {
        "date": "1980-06-14",
        "rank": "37",
        "song": "More Love",
        "artist": "Kim Carnes",
        "last-week": "65",
        "peak-rank": "37",
        "weeks-on-board": "3"
    },
    {
        "date": "1980-06-14",
        "rank": "38",
        "song": "All Night Long",
        "artist": "Joe Walsh",
        "last-week": "42",
        "peak-rank": "38",
        "weeks-on-board": "5"
    },
    {
        "date": "1980-06-14",
        "rank": "39",
        "song": "New Romance (It's A Mystery)",
        "artist": "Spider",
        "last-week": "39",
        "peak-rank": "39",
        "weeks-on-board": "9"
    },
    {
        "date": "1980-06-14",
        "rank": "40",
        "song": "I'm Alive",
        "artist": "Electric Light Orchestra",
        "last-week": "49",
        "peak-rank": "40",
        "weeks-on-board": "4"
    },
    {
        "date": "1980-06-14",
        "rank": "41",
        "song": "Angel Say No",
        "artist": "Tommy Tutone",
        "last-week": "48",
        "peak-rank": "41",
        "weeks-on-board": "4"
    },
    {
        "date": "1980-06-14",
        "rank": "42",
        "song": "Coming Down From Love",
        "artist": "Bobby Caldwell",
        "last-week": "43",
        "peak-rank": "42",
        "weeks-on-board": "9"
    },
    {
        "date": "1980-06-14",
        "rank": "43",
        "song": "Power",
        "artist": "The Temptations",
        "last-week": "44",
        "peak-rank": "43",
        "weeks-on-board": "6"
    },
    {
        "date": "1980-06-14",
        "rank": "44",
        "song": "Atomic",
        "artist": "Blondie",
        "last-week": "47",
        "peak-rank": "44",
        "weeks-on-board": "5"
    },
    {
        "date": "1980-06-14",
        "rank": "45",
        "song": "Clones (We're All)",
        "artist": "Alice Cooper",
        "last-week": "51",
        "peak-rank": "45",
        "weeks-on-board": "5"
    },
    {
        "date": "1980-06-14",
        "rank": "46",
        "song": "Stand By Me",
        "artist": "Mickey Gilley",
        "last-week": "58",
        "peak-rank": "46",
        "weeks-on-board": "5"
    },
    {
        "date": "1980-06-14",
        "rank": "47",
        "song": "Gimme Some Lovin'",
        "artist": "Blues Brothers",
        "last-week": "66",
        "peak-rank": "47",
        "weeks-on-board": "3"
    },
    {
        "date": "1980-06-14",
        "rank": "48",
        "song": "Ashes By Now",
        "artist": "Rodney Crowell",
        "last-week": "54",
        "peak-rank": "48",
        "weeks-on-board": "6"
    },
    {
        "date": "1980-06-14",
        "rank": "49",
        "song": "Misunderstanding",
        "artist": "Genesis",
        "last-week": "61",
        "peak-rank": "49",
        "weeks-on-board": "4"
    },
    {
        "date": "1980-06-14",
        "rank": "50",
        "song": "Is This Love",
        "artist": "Pat Travers Band",
        "last-week": "56",
        "peak-rank": "50",
        "weeks-on-board": "5"
    },
    {
        "date": "1980-06-14",
        "rank": "51",
        "song": "Somethin' 'Bout You Baby I Like",
        "artist": "Glen Campbell & Rita Coolidge",
        "last-week": "60",
        "peak-rank": "51",
        "weeks-on-board": "5"
    },
    {
        "date": "1980-06-14",
        "rank": "52",
        "song": "A Lover's Holiday",
        "artist": "Change",
        "last-week": "62",
        "peak-rank": "52",
        "weeks-on-board": "5"
    },
    {
        "date": "1980-06-14",
        "rank": "53",
        "song": "All Night Thing",
        "artist": "The Invisible Man's Band",
        "last-week": "55",
        "peak-rank": "53",
        "weeks-on-board": "5"
    },
    {
        "date": "1980-06-14",
        "rank": "54",
        "song": "Walks Like A Lady",
        "artist": "Journey",
        "last-week": "63",
        "peak-rank": "54",
        "weeks-on-board": "4"
    },
    {
        "date": "1980-06-14",
        "rank": "55",
        "song": "King Of The Hill",
        "artist": "Rick Pinette & Oak",
        "last-week": "59",
        "peak-rank": "55",
        "weeks-on-board": "6"
    },
    {
        "date": "1980-06-14",
        "rank": "56",
        "song": "Back Together Again",
        "artist": "Roberta Flack With Donny Hathaway",
        "last-week": "57",
        "peak-rank": "56",
        "weeks-on-board": "5"
    },
    {
        "date": "1980-06-14",
        "rank": "57",
        "song": "And The Cradle Will Rock...",
        "artist": "Van Halen",
        "last-week": "64",
        "peak-rank": "57",
        "weeks-on-board": "4"
    },
    {
        "date": "1980-06-14",
        "rank": "58",
        "song": "In America",
        "artist": "The Charlie Daniels Band",
        "last-week": "71",
        "peak-rank": "58",
        "weeks-on-board": "3"
    },
    {
        "date": "1980-06-14",
        "rank": "59",
        "song": "Everything Works If You Let It",
        "artist": "Cheap Trick",
        "last-week": "68",
        "peak-rank": "59",
        "weeks-on-board": "4"
    },
    {
        "date": "1980-06-14",
        "rank": "60",
        "song": "I Can't Help It",
        "artist": "Andy Gibb & Olivia Newton-John",
        "last-week": "24",
        "peak-rank": "12",
        "weeks-on-board": "12"
    },
    {
        "date": "1980-06-14",
        "rank": "61",
        "song": "Train In Vain (Stand By Me)",
        "artist": "The Clash",
        "last-week": "26",
        "peak-rank": "23",
        "weeks-on-board": "13"
    },
    {
        "date": "1980-06-14",
        "rank": "62",
        "song": "Gee Whiz",
        "artist": "Bernadette Peters",
        "last-week": "31",
        "peak-rank": "31",
        "weeks-on-board": "12"
    },
    {
        "date": "1980-06-14",
        "rank": "63",
        "song": "I Don't Want To Walk Without You",
        "artist": "Barry Manilow",
        "last-week": "36",
        "peak-rank": "36",
        "weeks-on-board": "10"
    },
    {
        "date": "1980-06-14",
        "rank": "64",
        "song": "With You I'm Born Again",
        "artist": "Billy Preston & Syreeta",
        "last-week": "40",
        "peak-rank": "4",
        "weeks-on-board": "28"
    },
    {
        "date": "1980-06-14",
        "rank": "65",
        "song": "Take Your Time (Do It Right) Part 1",
        "artist": "The S.O.S. Band",
        "last-week": "76",
        "peak-rank": "65",
        "weeks-on-board": "3"
    },
    {
        "date": "1980-06-14",
        "rank": "66",
        "song": "Love Stinks",
        "artist": "The J. Geils Band",
        "last-week": "38",
        "peak-rank": "38",
        "weeks-on-board": "10"
    },
    {
        "date": "1980-06-14",
        "rank": "67",
        "song": "Take You Tonight",
        "artist": "Ozark Mountain Daredevils",
        "last-week": "72",
        "peak-rank": "67",
        "weeks-on-board": "4"
    },
    {
        "date": "1980-06-14",
        "rank": "68",
        "song": "Empire Strikes Back (Medley)",
        "artist": "Meco",
        "last-week": "",
        "peak-rank": "68",
        "weeks-on-board": "1"
    },
    {
        "date": "1980-06-14",
        "rank": "69",
        "song": "Let My Love Open The Door",
        "artist": "Pete Townshend",
        "last-week": "",
        "peak-rank": "69",
        "weeks-on-board": "1"
    },
    {
        "date": "1980-06-14",
        "rank": "70",
        "song": "Slipstream",
        "artist": "Allan Clarke",
        "last-week": "70",
        "peak-rank": "70",
        "weeks-on-board": "4"
    },
    {
        "date": "1980-06-14",
        "rank": "71",
        "song": "All Out Of Love",
        "artist": "Air Supply",
        "last-week": "",
        "peak-rank": "71",
        "weeks-on-board": "1"
    },
    {
        "date": "1980-06-14",
        "rank": "72",
        "song": "It's For You",
        "artist": "Player",
        "last-week": "82",
        "peak-rank": "72",
        "weeks-on-board": "2"
    },
    {
        "date": "1980-06-14",
        "rank": "73",
        "song": "Shotgun Rider",
        "artist": "Joe Sun",
        "last-week": "77",
        "peak-rank": "73",
        "weeks-on-board": "3"
    },
    {
        "date": "1980-06-14",
        "rank": "74",
        "song": "JoJo",
        "artist": "Boz Scaggs",
        "last-week": "",
        "peak-rank": "74",
        "weeks-on-board": "1"
    },
    {
        "date": "1980-06-14",
        "rank": "75",
        "song": "You May Be Right",
        "artist": "Billy Joel",
        "last-week": "52",
        "peak-rank": "7",
        "weeks-on-board": "14"
    },
    {
        "date": "1980-06-14",
        "rank": "76",
        "song": "The Very Last Time",
        "artist": "Utopia",
        "last-week": "80",
        "peak-rank": "76",
        "weeks-on-board": "2"
    },
    {
        "date": "1980-06-14",
        "rank": "77",
        "song": "Sailing",
        "artist": "Christopher Cross",
        "last-week": "",
        "peak-rank": "77",
        "weeks-on-board": "1"
    },
    {
        "date": "1980-06-14",
        "rank": "78",
        "song": "Into The Night",
        "artist": "Benny Mardones",
        "last-week": "",
        "peak-rank": "78",
        "weeks-on-board": "1"
    },
    {
        "date": "1980-06-14",
        "rank": "79",
        "song": "Time For Me To Fly",
        "artist": "REO Speedwagon",
        "last-week": "89",
        "peak-rank": "56",
        "weeks-on-board": "10"
    },
    {
        "date": "1980-06-14",
        "rank": "80",
        "song": "The Seduction (Love Theme)",
        "artist": "James Last Band",
        "last-week": "46",
        "peak-rank": "28",
        "weeks-on-board": "12"
    },
    {
        "date": "1980-06-14",
        "rank": "81",
        "song": "The Blue Side",
        "artist": "Crystal Gayle",
        "last-week": "83",
        "peak-rank": "81",
        "weeks-on-board": "2"
    },
    {
        "date": "1980-06-14",
        "rank": "82",
        "song": "Happy Together (A Fantasy)",
        "artist": "Captain & Tennille",
        "last-week": "53",
        "peak-rank": "53",
        "weeks-on-board": "6"
    },
    {
        "date": "1980-06-14",
        "rank": "83",
        "song": "Sweet Sensation",
        "artist": "Stephanie Mills",
        "last-week": "",
        "peak-rank": "83",
        "weeks-on-board": "1"
    },
    {
        "date": "1980-06-14",
        "rank": "84",
        "song": "Back Of My Hand (I've Got Your Number)",
        "artist": "The Jags",
        "last-week": "86",
        "peak-rank": "84",
        "weeks-on-board": "2"
    },
    {
        "date": "1980-06-14",
        "rank": "85",
        "song": "I'm Happy Just To Dance With You",
        "artist": "Anne Murray",
        "last-week": "",
        "peak-rank": "85",
        "weeks-on-board": "1"
    },
    {
        "date": "1980-06-14",
        "rank": "86",
        "song": "Sisters Of The Moon",
        "artist": "Fleetwood Mac",
        "last-week": "88",
        "peak-rank": "86",
        "weeks-on-board": "2"
    },
    {
        "date": "1980-06-14",
        "rank": "87",
        "song": "Landlord",
        "artist": "Gladys Knight And The Pips",
        "last-week": "",
        "peak-rank": "87",
        "weeks-on-board": "1"
    },
    {
        "date": "1980-06-14",
        "rank": "88",
        "song": "Fame",
        "artist": "Irene Cara",
        "last-week": "",
        "peak-rank": "88",
        "weeks-on-board": "1"
    },
    {
        "date": "1980-06-14",
        "rank": "89",
        "song": "On The Rebound",
        "artist": "Russ Ballard",
        "last-week": "",
        "peak-rank": "89",
        "weeks-on-board": "1"
    },
    {
        "date": "1980-06-14",
        "rank": "90",
        "song": "One More Time For Love",
        "artist": "Billy Preston & Syreeta",
        "last-week": "",
        "peak-rank": "90",
        "weeks-on-board": "1"
    },
    {
        "date": "1980-06-14",
        "rank": "91",
        "song": "I Can Survive",
        "artist": "Triumph",
        "last-week": "91",
        "peak-rank": "91",
        "weeks-on-board": "2"
    },
    {
        "date": "1980-06-14",
        "rank": "92",
        "song": "Take A Little Rhythm",
        "artist": "Ali Thomson",
        "last-week": "",
        "peak-rank": "92",
        "weeks-on-board": "1"
    },
    {
        "date": "1980-06-14",
        "rank": "93",
        "song": "Only The Lonely (Have A Reason To Be Sad)",
        "artist": "La Flavour",
        "last-week": "",
        "peak-rank": "93",
        "weeks-on-board": "1"
    },
    {
        "date": "1980-06-14",
        "rank": "94",
        "song": "Don't Say Goodnight (It's Time For Love) (Parts 1 & 2)",
        "artist": "The Isley Brothers",
        "last-week": "67",
        "peak-rank": "39",
        "weeks-on-board": "9"
    },
    {
        "date": "1980-06-14",
        "rank": "95",
        "song": "Don't Push It Don't Force It",
        "artist": "Leon Haywood",
        "last-week": "73",
        "peak-rank": "49",
        "weeks-on-board": "11"
    },
    {
        "date": "1980-06-14",
        "rank": "96",
        "song": "Pilot Of The Airwaves",
        "artist": "Charlie Dore",
        "last-week": "74",
        "peak-rank": "13",
        "weeks-on-board": "17"
    },
    {
        "date": "1980-06-14",
        "rank": "97",
        "song": "Heart Hotels",
        "artist": "Dan Fogelberg",
        "last-week": "69",
        "peak-rank": "21",
        "weeks-on-board": "13"
    },
    {
        "date": "1980-06-14",
        "rank": "98",
        "song": "Love And Loneliness",
        "artist": "The Motors",
        "last-week": "78",
        "peak-rank": "78",
        "weeks-on-board": "5"
    },
    {
        "date": "1980-06-14",
        "rank": "99",
        "song": "Run Like Hell",
        "artist": "Pink Floyd",
        "last-week": "75",
        "peak-rank": "53",
        "weeks-on-board": "6"
    },
    {
        "date": "1980-06-14",
        "rank": "100",
        "song": "Let Me Be The Clock",
        "artist": "Smokey Robinson",
        "last-week": "85",
        "peak-rank": "31",
        "weeks-on-board": "14"
    }
]